Workbook

Sheet Параметры
A1: ПАРАМЕТРЫ ОБЪЕКТА (редактируйте синие ячейки на жёлтом фоне)
A3: Параметр | B3: Значение | C3: Комментарий
A4: Общая площадь квартиры, м² (с лоджией) | B4: 55.1 | C4: по плану кв. 312: жилая 25.4 / общая 52.4 / с лоджией 55.1
A5: Площадь пола под ламинат/SPC, м² | B5: 42 | C5: спальня 11.7 + гостиная/детская 13.7 + кухня 10.3 + часть прихожей ≈ 6 (у входа — керамогранит, видно на видео)
A6: Запас на подрезку, % | B6: 0.07 | C6: 7% для прямой укладки, 10–12% для диагонали/ёлочки
A7: Площадь натяжных потолков, м² | B7: 52.4 | C7: по плану: 13.7+11.7+10.3+11.8+2.8+2.1 (лоджия не считается)
A8: Периметр плинтуса, п.м | B8: 50 | C8: спальня ≈14 + детская ≈15 + кухня-гостиная ≈21 п.м
A9: Розетки, шт | B9: 30 | C9: типовая 2-комн. 55 м²: кухня 8–10, комнаты 6–8 каждая, коридор 2, санузлы 2
A10: Выключатели, шт | B10: 8
A11: Рамки, шт | B11: 25 | C11: часть розеток блоками по 2–3 в одной рамке
A12: Точки света на потолке, шт | B12: 12 | C12: точечные/трек + люстры; уточнить по вашему плану
A13: Санузлов, шт | B13: 2 | C13: по видео: №1 с унитазом и колонкой, №2 с душевым подиумом
A14: Раковин, шт | B14: 2 | C14: по одной в каждый санузел
A15: Площадь стен под обои, м² | B15: 120 | C15: периметр ≈ 52 п.м (после сноса стены кухня–прихожая) × h 2.7 = 140 минус окна и проёмы ≈ 20; санузлы в плитке
A16: Дверей стандартных 800 мм, шт | B16: 3 | C16: спальня, ванная, с/у (кухня — стена снесена, двери нет)
A17: Дверей широких (детская, проём расширен), шт | B17: 1 | C17: двустворчатая или раздвижная — по заметке брата проём сделан широким
A18: Резерв на непредвиденное, % | B18: 0.1 | C18: рекомендуется 10–15%
A21: Легенда:
A22: Синий текст на жёлтом — вводные, которые вы меняете. Чёрный — формулы. Зелёный — ссылки на другой лист.
A23: Цены — ориентир по Саратову на сентябрь 2026 (Лемана ПРО Саратов, Профком, Сантехника.ру Саратов, Profi.ru Саратов, сайты потолочных компаний). Перед закупкой сверьте по ссылкам на листе «Закупка_ссылки».

Sheet 1_Ремонт
A1: 1. РЕМОНТ: ПОЛ, ПОТОЛКИ, САНТЕХНИКА, ЭЛЕКТРИКА, ОБОИ, ДВЕРИ — 3 ОПЦИИ + РЕАЛ — квартира 55 м², Саратов, сентябрь 2026
A2: Цены за единицу (F, H, J) — синие, правьте. Столбец M «Выбор РЕАЛ» — выпадающий список МИН/СРЕД/МАКС для реалистичной сборки, столбец N считает её сумму.
A4: № | B4: Раздел | C4: Позиция | D4: Ед. | E4: Кол-во | F4: Цена МИН | G4: Сумма МИН | H4: Цена СРЕД | I4: Сумма СРЕД | J4: Цена МАКС | K4: Сумма МАКС | L4: Примечание | M4: Выбор РЕАЛ | N4: Сумма РЕАЛ
A5: 1. ПОЛ — материалы
A6: 1 | B6: 1. Пол | C6: Напольное покрытие (ламинат / SPC) | D6: м² | E6: =ROUND(Параметры!$B$5*(1+Параметры!$B$6),0) -> 45 | F6: 700 | G6: =E6*F6 -> 31500 | H6: 1150 | I6: =E6*H6 -> 51750 | J6: 2300 | K6: =E6*J6 -> 103500 | L6: МИН: ламинат 32 кл 8 мм · СРЕД: ламинат 33 кл 8–10 мм влагостойкий с фаской · МАКС: SPC-кварцвинил 43 кл 4–5 мм | M6: СРЕД | N6: =IF(M6="МИН",G6,IF(M6="МАКС",K6,I6)) -> 51750
A7: 2 | B7: 1. Пол | C7: Подложка | D7: м² | E7: =ROUND(Параметры!$B$5*(1+Параметры!$B$6),0) -> 45 | F7: 100 | G7: =E7*F7 -> 4500 | H7: 200 | I7: =E7*H7 -> 9000 | J7: 350 | K7: =E7*J7 -> 15750 | L7: МИН: вспененный ПЭ 2 мм · СРЕД: XPS/Arbiton 3 мм · МАКС: пробка/IXPE 1.5 мм под SPC | M7: СРЕД | N7: =IF(M7="МИН",G7,IF(M7="МАКС",K7,I7)) -> 9000
A8: 3 | B8: 1. Пол | C8: Плёнка пароизоляция 200 мкм | D8: м² | E8: =ROUND(Параметры!$B$5*(1+Параметры!$B$6),0) -> 45 | F8: 30 | G8: =E8*F8 -> 1350 | H8: 40 | I8: =E8*H8 -> 1800 | J8: 40 | K8: =E8*J8 -> 1800 | L8: по стяжке обязательно | M8: СРЕД | N8: =IF(M8="МИН",G8,IF(M8="МАКС",K8,I8)) -> 1800
A9: 4 | B9: 1. Пол | C9: Плинтус напольный | D9: п.м | E9: =Параметры!$B$8 -> 50 | F9: 130 | G9: =E9*F9 -> 6500 | H9: 350 | I9: =E9*H9 -> 17500 | J9: 800 | K9: =E9*J9 -> 40000 | L9: МИН: ПВХ с кабель-каналом · СРЕД: МДФ/дюрополимер 80 мм · МАКС: скрытый алюминиевый / дюрополимер под покраску 100 мм | M9: СРЕД | N9: =IF(M9="МИН",G9,IF(M9="МАКС",K9,I9)) -> 17500
A10: 5 | B10: 1. Пол | C10: Порожки, стыки плитка–ламинат | D10: компл | E10: 1 | F10: 1500 | G10: =E10*F10 -> 1500 | H10: 3000 | I10: =E10*H10 -> 3000 | J10: 6000 | K10: =E10*J10 -> 6000 | L10: у входов в коридор и санузлы (по видео там керамогранит) | M10: СРЕД | N10: =IF(M10="МИН",G10,IF(M10="МАКС",K10,I10)) -> 3000
A11: 2. ПОТОЛОК — материалы и потолок «под ключ»
A12: 6 | B12: 2. Потолок | C12: Натяжной потолок с монтажом «под ключ» | D12: м² | E12: =Параметры!$B$7 -> 52.4 | F12: 400 | G12: =E12*F12 -> 20960 | H12: 950 | I12: =E12*H12 -> 49780 | J12: 1800 | K12: =E12*J12 -> 94320 | L12: МИН: ПВХ матовый MSD · СРЕД: Bauf/тканевый + теневой профиль · МАКС: тканевый Descor + теневой профиль + парящий/световые линии | M12: СРЕД | N12: =IF(M12="МИН",G12,IF(M12="МАКС",K12,I12)) -> 49780
A13: 7 | B13: 2. Потолок | C13: Закладные (брус/платформы) под люстры, карнизы | D13: компл | E13: 1 | F13: 2000 | G13: =E13*F13 -> 2000 | H13: 4000 | I13: =E13*H13 -> 4000 | J13: 8000 | K13: =E13*J13 -> 8000 | L13: ставится ДО натяжки | M13: СРЕД | N13: =IF(M13="МИН",G13,IF(M13="МАКС",K13,I13)) -> 4000
A14: 8 | B14: 2. Потолок | C14: Кабель ВВГнг-LS + гофра для потолочных линий | D14: компл | E14: 1 | F14: 6000 | G14: =E14*F14 -> 6000 | H14: 12000 | I14: =E14*H14 -> 12000 | J14: 20000 | K14: =E14*J14 -> 20000 | M14: СРЕД | N14: =IF(M14="МИН",G14,IF(M14="МАКС",K14,I14)) -> 12000
A15: 9 | B15: 2. Потолок | C15: Светильники потолочные | D15: шт | E15: =Параметры!$B$12 -> 12 | F15: 250 | G15: =E15*F15 -> 3000 | H15: 700 | I15: =E15*H15 -> 8400 | J15: 2500 | K15: =E15*J15 -> 30000 | L15: МИН: GX53 накладные · СРЕД: точечные LED + 2 люстры · МАКС: магнитный трек + дизайнерские | M15: СРЕД | N15: =IF(M15="МИН",G15,IF(M15="МАКС",K15,I15)) -> 8400
A16: 10 | B16: 2. Потолок | C16: Ниша ГКЛ под скрытый карниз (материалы) | D16: компл | E16: 1 | F16: 0 | G16: =E16*F16 -> 0 | H16: 5000 | I16: =E16*H16 -> 5000 | J16: 12000 | K16: =E16*J16 -> 12000 | L16: в МИН не делаем — карниз накладной | M16: СРЕД | N16: =IF(M16="МИН",G16,IF(M16="МАКС",K16,I16)) -> 5000
A17: 3. САНТЕХНИКА — материалы
A18: 11 | B18: 3. Сантехника | C18: Унитаз | D18: шт | E18: 1 | F18: 8000 | G18: =E18*F18 -> 8000 | H18: 18000 | I18: =E18*H18 -> 18000 | J18: 45000 | K18: =E18*J18 -> 45000 | L18: МИН: компакт Cersanit Trento · СРЕД: безободковый с микролифтом Cersanit City / Roca Gap · МАКС: инсталляция Geberit Duofix + подвесной Geberit iCon/Roca | M18: СРЕД | N18: =IF(M18="МИН",G18,IF(M18="МАКС",K18,I18)) -> 18000
A19: 12 | B19: 3. Сантехника | C19: Раковина (умывальник) | D19: шт | E19: =Параметры!$B$14 -> 2 | F19: 3000 | G19: =E19*F19 -> 6000 | H19: 8000 | I19: =E19*H19 -> 16000 | J19: 18000 | K19: =E19*J19 -> 36000 | M19: СРЕД | N19: =IF(M19="МИН",G19,IF(M19="МАКС",K19,I19)) -> 16000
A20: 13 | B20: 3. Сантехника | C20: Смеситель для раковины | D20: шт | E20: =Параметры!$B$14 -> 2 | F20: 2500 | G20: =E20*F20 -> 5000 | H20: 7000 | I20: =E20*H20 -> 14000 | J20: 18000 | K20: =E20*J20 -> 36000 | L20: МИН: Iddis/Esko · СРЕД: Lemark Plus / Grohe BauEdge · МАКС: Hansgrohe Talis / Grohe Essence | M20: СРЕД | N20: =IF(M20="МИН",G20,IF(M20="МАКС",K20,I20)) -> 14000
A21: 14 | B21: 3. Сантехника | C21: Сифон + подводки для раковины | D21: шт | E21: =Параметры!$B$14 -> 2 | F21: 700 | G21: =E21*F21 -> 1400 | H21: 1500 | I21: =E21*H21 -> 3000 | J21: 3500 | K21: =E21*J21 -> 7000 | M21: СРЕД | N21: =IF(M21="МИН",G21,IF(M21="МАКС",K21,I21)) -> 3000
A22: 15 | B22: 3. Сантехника | C22: Тумба под раковину | D22: шт | E22: =Параметры!$B$14 -> 2 | F22: 6000 | G22: =E22*F22 -> 12000 | H22: 18000 | I22: =E22*H22 -> 36000 | J22: 45000 | K22: =E22*J22 -> 90000 | L22: МИН: Sensea/Runo · СРЕД: Aquaton/Style Line · МАКС: Jacob Delafon / Cezares | M22: СРЕД | N22: =IF(M22="МИН",G22,IF(M22="МАКС",K22,I22)) -> 36000
A23: 16 | B23: 3. Сантехника | C23: Смеситель для душа + душевая стойка | D23: компл | E23: 1 | F23: 4000 | G23: =E23*F23 -> 4000 | H23: 15000 | I23: =E23*H23 -> 15000 | J23: 45000 | K23: =E23*J23 -> 45000 | L23: выводы под смеситель на видео готовы (открытый монтаж) | M23: СРЕД | N23: =IF(M23="МИН",G23,IF(M23="МАКС",K23,I23)) -> 15000
A24: 17 | B24: 3. Сантехника | C24: Ограждение душевого подиума | D24: шт | E24: 1 | F24: 3000 | G24: =E24*F24 -> 3000 | H24: 30000 | I24: =E24*H24 -> 30000 | J24: 60000 | K24: =E24*J24 -> 60000 | L24: МИН: штанга + шторка · СРЕД: стекло 8 мм на заказ (Walk-In) · МАКС: стекло 10 мм + дверь, чёрная/латунная фурнитура | M24: СРЕД | N24: =IF(M24="МИН",G24,IF(M24="МАКС",K24,I24)) -> 30000
A25: 18 | B25: 3. Сантехника | C25: Гигиенический душ | D25: компл | E25: 1 | F25: 2500 | G25: =E25*F25 -> 2500 | H25: 7000 | I25: =E25*H25 -> 7000 | J25: 15000 | K25: =E25*J25 -> 15000 | M25: СРЕД | N25: =IF(M25="МИН",G25,IF(M25="МАКС",K25,I25)) -> 7000
A26: 19 | B26: 3. Сантехника | C26: Полотенцесушитель электрический | D26: шт | E26: 1 | F26: 4000 | G26: =E26*F26 -> 4000 | H26: 12000 | I26: =E26*H26 -> 12000 | J26: 25000 | K26: =E26*J26 -> 25000 | L26: электрический — под него нужна розетка/вывод | M26: СРЕД | N26: =IF(M26="МИН",G26,IF(M26="МАКС",K26,I26)) -> 12000
A27: 20 | B27: 3. Сантехника | C27: Зеркало / зеркальный шкаф | D27: шт | E27: =Параметры!$B$14 -> 2 | F27: 1500 | G27: =E27*F27 -> 3000 | H27: 6000 | I27: =E27*H27 -> 12000 | J27: 15000 | K27: =E27*J27 -> 30000 | M27: СРЕД | N27: =IF(M27="МИН",G27,IF(M27="МАКС",K27,I27)) -> 12000
A28: 21 | B28: 3. Сантехника | C28: Вентилятор вытяжной | D28: шт | E28: =Параметры!$B$13 -> 2 | F28: 800 | G28: =E28*F28 -> 1600 | H28: 3000 | I28: =E28*H28 -> 6000 | J28: 7000 | K28: =E28*J28 -> 14000 | L28: МАКС: Soler&Palau Silent с таймером | M28: СРЕД | N28: =IF(M28="МИН",G28,IF(M28="МАКС",K28,I28)) -> 6000
A29: 22 | B29: 3. Сантехника | C29: Аксессуары (держатели, ёршик, крючки, дозатор) | D29: компл | E29: 1 | F29: 2500 | G29: =E29*F29 -> 2500 | H29: 7000 | I29: =E29*H29 -> 7000 | J29: 20000 | K29: =E29*J29 -> 20000 | M29: СРЕД | N29: =IF(M29="МИН",G29,IF(M29="МАКС",K29,I29)) -> 7000
A30: 23 | B30: 3. Сантехника | C30: Люк ревизионный к колонке/стоякам | D30: шт | E30: 1 | F30: 2000 | G30: =E30*F30 -> 2000 | H30: 5000 | I30: =E30*H30 -> 5000 | J30: 12000 | K30: =E30*J30 -> 12000 | L30: МАКС: нажимной скрытый под плитку | M30: СРЕД | N30: =IF(M30="МИН",G30,IF(M30="МАКС",K30,I30)) -> 5000
A31: 24 | B31: 3. Сантехника | C31: Расходники (краны, гибкая подводка, ФУМ, силикон) | D31: компл | E31: 1 | F31: 3000 | G31: =E31*F31 -> 3000 | H31: 6000 | I31: =E31*H31 -> 6000 | J31: 10000 | K31: =E31*J31 -> 10000 | M31: СРЕД | N31: =IF(M31="МИН",G31,IF(M31="МАКС",K31,I31)) -> 6000
A32: 4. ЭЛЕКТРИКА — материалы
A33: 25 | B33: 4. Электрика | C33: Розетка (механизм) | D33: шт | E33: =Параметры!$B$9 -> 30 | F33: 200 | G33: =E33*F33 -> 6000 | H33: 900 | I33: =E33*H33 -> 27000 | J33: 2200 | K33: =E33*J33 -> 66000 | L33: МИН: Systeme Electric Этюд/Glossa · СРЕД: Werkel / AtlasDesign · МАКС: Legrand Valena Life / Jung / Gira | M33: СРЕД | N33: =IF(M33="МИН",G33,IF(M33="МАКС",K33,I33)) -> 27000
A34: 26 | B34: 4. Электрика | C34: Выключатель (механизм) | D34: шт | E34: =Параметры!$B$10 -> 8 | F34: 200 | G34: =E34*F34 -> 1600 | H34: 900 | I34: =E34*H34 -> 7200 | J34: 2500 | K34: =E34*J34 -> 20000 | M34: СРЕД | N34: =IF(M34="МИН",G34,IF(M34="МАКС",K34,I34)) -> 7200
A35: 27 | B35: 4. Электрика | C35: Рамки | D35: шт | E35: =Параметры!$B$11 -> 25 | F35: 60 | G35: =E35*F35 -> 1500 | H35: 250 | I35: =E35*H35 -> 6250 | J35: 800 | K35: =E35*J35 -> 20000 | M35: СРЕД | N35: =IF(M35="МИН",G35,IF(M35="МАКС",K35,I35)) -> 6250
A36: 28 | B36: 4. Электрика | C36: Подрозетники | D36: шт | E36: =Параметры!$B$9+Параметры!$B$10 -> 38 | F36: 60 | G36: =E36*F36 -> 2280 | H36: 60 | I36: =E36*H36 -> 2280 | J36: 60 | K36: =E36*J36 -> 2280 | L36: если уже вмурованы — поставьте 0 | M36: СРЕД | N36: =IF(M36="МИН",G36,IF(M36="МАКС",K36,I36)) -> 2280
A37: 29 | B37: 4. Электрика | C37: Щит в сборе (бокс, автоматы, УЗО/дифы, реле напряжения) | D37: компл | E37: 1 | F37: 8000 | G37: =E37*F37 -> 8000 | H37: 25000 | I37: =E37*H37 -> 25000 | J37: 60000 | K37: =E37*J37 -> 60000 | L37: МИН: IEK/EKF · СРЕД: Schneider Easy9 / ABB Basic M + реле напряжения · МАКС: ABB S200 / Hager + дифавтоматы + УЗИП | M37: СРЕД | N37: =IF(M37="МИН",G37,IF(M37="МАКС",K37,I37)) -> 25000
A38: 30 | B38: 4. Электрика | C38: Кабель на доделку линий | D38: компл | E38: 1 | F38: 3000 | G38: =E38*F38 -> 3000 | H38: 6000 | I38: =E38*H38 -> 6000 | J38: 10000 | K38: =E38*J38 -> 10000 | M38: СРЕД | N38: =IF(M38="МИН",G38,IF(M38="МАКС",K38,I38)) -> 6000
A39: 31 | B39: 4. Электрика | C39: Выделенная линия на электроварочную (ВВГнг 3×6 + автомат 32А + розетка 32А) | D39: компл | E39: 1 | F39: 3500 | G39: =E39*F39 -> 3500 | H39: 4500 | I39: =E39*H39 -> 4500 | J39: 6000 | K39: =E39*J39 -> 6000 | L39: варочная электрическая — обязательна отдельная линия от щита | M39: СРЕД | N39: =IF(M39="МИН",G39,IF(M39="МАКС",K39,I39)) -> 4500
A40: 5. ФИНИШ СТЕН (ОБОИ) — материалы
A41: 32 | B41: 5. Стены | C41: Обои | D41: м² | E41: =Параметры!$B$15 -> 120 | F41: 200 | G41: =E41*F41 -> 24000 | H41: 450 | I41: =E41*H41 -> 54000 | J41: 1200 | K41: =E41*J41 -> 144000 | L41: МИН: виниловые на флизелине (Лемана, ~1 100 ₽/рулон 5.3 м²) · СРЕД: флизелиновые Erismann/Marburg, под подбор рисунка · МАКС: дизайнерские/текстильные, широкий рулон. Расход ≈ +10% на подбор | M41: СРЕД | N41: =IF(M41="МИН",G41,IF(M41="МАКС",K41,I41)) -> 54000
A42: 33 | B42: 5. Стены | C42: Клей, грунт, малярные расходники | D42: компл | E42: 1 | F42: 4000 | G42: =E42*F42 -> 4000 | H42: 7000 | I42: =E42*H42 -> 7000 | J42: 12000 | K42: =E42*J42 -> 12000 | M42: СРЕД | N42: =IF(M42="МИН",G42,IF(M42="МАКС",K42,I42)) -> 7000
A43: 34 | B43: 5. Стены | C43: Акцентная стена (краска/панели/декоративка) — зал и детская | D43: компл | E43: 1 | F43: 0 | G43: =E43*F43 -> 0 | H43: 15000 | I43: =E43*H43 -> 15000 | J43: 60000 | K43: =E43*J43 -> 60000 | L43: в МИН не делаем; СРЕД: краска + рейки; МАКС: микроцемент/панели | M43: СРЕД | N43: =IF(M43="МИН",G43,IF(M43="МАКС",K43,I43)) -> 15000
A44: 6. ДВЕРИ — материалы, поштучно
A45: 35 | B45: 6. Двери | C45: Дверь стандартная 800 мм: полотно + короб + наличники + ручка + петли | D45: шт | E45: =Параметры!$B$16 -> 3 | F45: 8000 | G45: =E45*F45 -> 24000 | H45: 18000 | I45: =E45*H45 -> 54000 | J45: 45000 | K45: =E45*J45 -> 135000 | L45: спальня, ванная, с/у · МИН: ламинированные Лемана · СРЕД: экошпон/ПВХ с врезкой · МАКС: эмаль/шпон, скрытый короб. В санузлы — влагостойкое полотно | M45: СРЕД | N45: =IF(M45="МИН",G45,IF(M45="МАКС",K45,I45)) -> 54000
A46: 36 | B46: 6. Двери | C46: Дверь широкая в детскую (двустворчатая 1200–1400 или раздвижная): полотна + короб + фурнитура | D46: шт | E46: =Параметры!$B$17 -> 1 | F46: 16000 | G46: =E46*F46 -> 16000 | H46: 35000 | I46: =E46*H46 -> 35000 | J46: 90000 | K46: =E46*J46 -> 90000 | L46: проём расширен — двустворчатая экошпон (СРЕД) или раздвижная в пенале/стеклянная (МАКС). МИН — распашная двустворчатая ламинированная | M46: СРЕД | N46: =IF(M46="МИН",G46,IF(M46="МАКС",K46,I46)) -> 35000
A47: 37 | B47: 6. Двери | C47: Доборы, порожки, уплотнители | D47: компл | E47: 1 | F47: 3000 | G47: =E47*F47 -> 3000 | H47: 6000 | I47: =E47*H47 -> 6000 | J47: 12000 | K47: =E47*J47 -> 12000 | L47: доборы нужны при толщине стены > 70 мм | M47: СРЕД | N47: =IF(M47="МИН",G47,IF(M47="МАКС",K47,I47)) -> 6000
A48: 7. РАБОТЫ — отдельной статьёй
A49: 38 | B49: 7. Работы | C49: Подготовка основания пола (грунт, ровнитель) | D49: компл | E49: 1 | F49: 5000 | G49: =E49*F49 -> 5000 | H49: 12000 | I49: =E49*H49 -> 12000 | J49: 25000 | K49: =E49*J49 -> 25000 | L49: МАКС: тонкий наливной пол по всей площади | M49: СРЕД | N49: =IF(M49="МИН",G49,IF(M49="МАКС",K49,I49)) -> 12000
A50: 39 | B50: 7. Работы | C50: Укладка напольного покрытия | D50: м² | E50: =Параметры!$B$5 -> 42 | F50: 300 | G50: =E50*F50 -> 12600 | H50: 450 | I50: =E50*H50 -> 18900 | J50: 700 | K50: =E50*J50 -> 29400 | L50: Profi.ru Саратов: от 200–300 ₽/м²; МАКС — SPC/диагональ | M50: СРЕД | N50: =IF(M50="МИН",G50,IF(M50="МАКС",K50,I50)) -> 18900
A51: 40 | B51: 7. Работы | C51: Монтаж плинтуса | D51: п.м | E51: =Параметры!$B$8 -> 50 | F51: 150 | G51: =E51*F51 -> 7500 | H51: 250 | I51: =E51*H51 -> 12500 | J51: 400 | K51: =E51*J51 -> 20000 | M51: СРЕД | N51: =IF(M51="МИН",G51,IF(M51="МАКС",K51,I51)) -> 12500
A52: 41 | B52: 7. Работы | C52: Электрика под потолок (разводка точек света) | D52: компл | E52: 1 | F52: 6000 | G52: =E52*F52 -> 6000 | H52: 12000 | I52: =E52*H52 -> 12000 | J52: 25000 | K52: =E52*J52 -> 25000 | L52: делается ДО натяжного потолка | M52: СРЕД | N52: =IF(M52="МИН",G52,IF(M52="МАКС",K52,I52)) -> 12000
A53: 42 | B53: 7. Работы | C53: Ниша ГКЛ под скрытый карниз | D53: компл | E53: 1 | F53: 0 | G53: =E53*F53 -> 0 | H53: 8000 | I53: =E53*H53 -> 8000 | J53: 15000 | K53: =E53*J53 -> 15000 | M53: СРЕД | N53: =IF(M53="МИН",G53,IF(M53="МАКС",K53,I53)) -> 8000
A54: 43 | B54: 7. Работы | C54: Монтаж натяжного потолка | D54: компл | E54: 1 | F54: 0 | G54: =E54*F54 -> 0 | H54: 0 | I54: =E54*H54 -> 0 | J54: 0 | K54: =E54*J54 -> 0 | L54: уже входит в цену «под ключ» в разделе 2 | M54: СРЕД | N54: =IF(M54="МИН",G54,IF(M54="МАКС",K54,I54)) -> 0
A55: 44 | B55: 7. Работы | C55: Установка унитаза | D55: шт | E55: 1 | F55: 2500 | G55: =E55*F55 -> 2500 | H55: 4000 | I55: =E55*H55 -> 4000 | J55: 9000 | K55: =E55*J55 -> 9000 | L55: МАКС — с инсталляцией и коробом | M55: СРЕД | N55: =IF(M55="МИН",G55,IF(M55="МАКС",K55,I55)) -> 4000
A56: 45 | B56: 7. Работы | C56: Установка раковины со смесителем и тумбой | D56: шт | E56: =Параметры!$B$14 -> 2 | F56: 2500 | G56: =E56*F56 -> 5000 | H56: 4000 | I56: =E56*H56 -> 8000 | J56: 6000 | K56: =E56*J56 -> 12000 | M56: СРЕД | N56: =IF(M56="МИН",G56,IF(M56="МАКС",K56,I56)) -> 8000
A57: 46 | B57: 7. Работы | C57: Подключение душевого смесителя/стойки | D57: компл | E57: 1 | F57: 2000 | G57: =E57*F57 -> 2000 | H57: 3500 | I57: =E57*H57 -> 3500 | J57: 8000 | K57: =E57*J57 -> 8000 | M57: СРЕД | N57: =IF(M57="МИН",G57,IF(M57="МАКС",K57,I57)) -> 3500
A58: 47 | B58: 7. Работы | C58: Установка полотенцесушителя | D58: шт | E58: 1 | F58: 1500 | G58: =E58*F58 -> 1500 | H58: 3000 | I58: =E58*H58 -> 3000 | J58: 4000 | K58: =E58*J58 -> 4000 | M58: СРЕД | N58: =IF(M58="МИН",G58,IF(M58="МАКС",K58,I58)) -> 3000
A59: 48 | B59: 7. Работы | C59: Установка гигиенического душа | D59: шт | E59: 1 | F59: 1500 | G59: =E59*F59 -> 1500 | H59: 2500 | I59: =E59*H59 -> 2500 | J59: 4000 | K59: =E59*J59 -> 4000 | M59: СРЕД | N59: =IF(M59="МИН",G59,IF(M59="МАКС",K59,I59)) -> 2500
A60: 49 | B60: 7. Работы | C60: Монтаж ограждения душевой | D60: шт | E60: 1 | F60: 3000 | G60: =E60*F60 -> 3000 | H60: 8000 | I60: =E60*H60 -> 8000 | J60: 12000 | K60: =E60*J60 -> 12000 | L60: у стекольщиков часто входит в цену стекла | M60: СРЕД | N60: =IF(M60="МИН",G60,IF(M60="МАКС",K60,I60)) -> 8000
A61: 50 | B61: 7. Работы | C61: Люк, вентиляторы, мелкие подключения | D61: компл | E61: 1 | F61: 2000 | G61: =E61*F61 -> 2000 | H61: 4000 | I61: =E61*H61 -> 4000 | J61: 6000 | K61: =E61*J61 -> 6000 | M61: СРЕД | N61: =IF(M61="МИН",G61,IF(M61="МАКС",K61,I61)) -> 4000
A62: 51 | B62: 7. Работы | C62: Установка розеток и выключателей | D62: шт | E62: =Параметры!$B$9+Параметры!$B$10 -> 38 | F62: 250 | G62: =E62*F62 -> 9500 | H62: 400 | I62: =E62*H62 -> 15200 | J62: 600 | K62: =E62*J62 -> 22800 | M62: СРЕД | N62: =IF(M62="МИН",G62,IF(M62="МАКС",K62,I62)) -> 15200
A63: 52 | B63: 7. Работы | C63: Сборка и подключение щита | D63: компл | E63: 1 | F63: 6000 | G63: =E63*F63 -> 6000 | H63: 15000 | I63: =E63*H63 -> 15000 | J63: 25000 | K63: =E63*J63 -> 25000 | M63: СРЕД | N63: =IF(M63="МИН",G63,IF(M63="МАКС",K63,I63)) -> 15000
A64: 53 | B64: 7. Работы | C64: Монтаж линии на варочную панель | D64: компл | E64: 1 | F64: 2500 | G64: =E64*F64 -> 2500 | H64: 3500 | I64: =E64*H64 -> 3500 | J64: 5000 | K64: =E64*J64 -> 5000 | M64: СРЕД | N64: =IF(M64="МИН",G64,IF(M64="МАКС",K64,I64)) -> 3500
A65: 54 | B65: 7. Работы | C65: Прозвонка, маркировка, проверка линий | D65: компл | E65: 1 | F65: 2000 | G65: =E65*F65 -> 2000 | H65: 4000 | I65: =E65*H65 -> 4000 | J65: 6000 | K65: =E65*J65 -> 6000 | M65: СРЕД | N65: =IF(M65="МИН",G65,IF(M65="МАКС",K65,I65)) -> 4000
A66: 55 | B66: 7. Работы | C66: Поклейка обоев | D66: м² | E66: =Параметры!$B$15 -> 120 | F66: 250 | G66: =E66*F66 -> 30000 | H66: 350 | I66: =E66*H66 -> 42000 | J66: 600 | K66: =E66*J66 -> 72000 | L66: МАКС — обои с подбором/текстиль | M66: СРЕД | N66: =IF(M66="МИН",G66,IF(M66="МАКС",K66,I66)) -> 42000
A67: 56 | B67: 7. Работы | C67: Акцентная стена (работа) | D67: компл | E67: 1 | F67: 0 | G67: =E67*F67 -> 0 | H67: 8000 | I67: =E67*H67 -> 8000 | J67: 30000 | K67: =E67*J67 -> 30000 | M67: СРЕД | N67: =IF(M67="МИН",G67,IF(M67="МАКС",K67,I67)) -> 8000
A68: 57 | B68: 7. Работы | C68: Установка стандартной двери | D68: шт | E68: =Параметры!$B$16 -> 3 | F68: 4000 | G68: =E68*F68 -> 12000 | H68: 6000 | I68: =E68*H68 -> 18000 | J68: 10000 | K68: =E68*J68 -> 30000 | M68: СРЕД | N68: =IF(M68="МИН",G68,IF(M68="МАКС",K68,I68)) -> 18000
A69: 58 | B69: 7. Работы | C69: Установка широкой/раздвижной двери | D69: шт | E69: =Параметры!$B$17 -> 1 | F69: 7000 | G69: =E69*F69 -> 7000 | H69: 10000 | I69: =E69*H69 -> 10000 | J69: 20000 | K69: =E69*J69 -> 20000 | M69: СРЕД | N69: =IF(M69="МИН",G69,IF(M69="МАКС",K69,I69)) -> 10000
A70: 59 | B70: 7. Работы | C70: Финальная уборка (клининг) | D70: компл | E70: 1 | F70: 0 | G70: =E70*F70 -> 0 | H70: 8000 | I70: =E70*H70 -> 8000 | J70: 15000 | K70: =E70*J70 -> 15000 | M70: СРЕД | N70: =IF(M70="МИН",G70,IF(M70="МАКС",K70,I70)) -> 8000
A71: 60 | B71: 7. Работы | C71: Доставка, подъём, вынос мусора | D71: компл | E71: 1 | F71: 8000 | G71: =E71*F71 -> 8000 | H71: 15000 | I71: =E71*H71 -> 15000 | J71: 25000 | K71: =E71*J71 -> 25000 | M71: СРЕД | N71: =IF(M71="МИН",G71,IF(M71="МАКС",K71,I71)) -> 15000
C73: ИТОГИ ПО РАЗДЕЛАМ
C74: 1. ПОЛ — материалы | G74: =SUM(G6:G10) -> 45350 | I74: =SUM(I6:I10) -> 83050 | K74: =SUM(K6:K10) -> 167050 | N74: =SUM(N6:N10) -> 83050
C75: 2. ПОТОЛОК — материалы и потолок «под ключ» | G75: =SUM(G12:G16) -> 31960 | I75: =SUM(I12:I16) -> 79180 | K75: =SUM(K12:K16) -> 164320 | N75: =SUM(N12:N16) -> 79180
C76: 3. САНТЕХНИКА — материалы | G76: =SUM(G18:G31) -> 58000 | I76: =SUM(I18:I31) -> 187000 | K76: =SUM(K18:K31) -> 445000 | N76: =SUM(N18:N31) -> 187000
C77: 4. ЭЛЕКТРИКА — материалы | G77: =SUM(G33:G39) -> 25880 | I77: =SUM(I33:I39) -> 78230 | K77: =SUM(K33:K39) -> 184280 | N77: =SUM(N33:N39) -> 78230
C78: 5. ФИНИШ СТЕН (ОБОИ) — материалы | G78: =SUM(G41:G43) -> 28000 | I78: =SUM(I41:I43) -> 76000 | K78: =SUM(K41:K43) -> 216000 | N78: =SUM(N41:N43) -> 76000
C79: 6. ДВЕРИ — материалы, поштучно | G79: =SUM(G45:G47) -> 43000 | I79: =SUM(I45:I47) -> 95000 | K79: =SUM(K45:K47) -> 237000 | N79: =SUM(N45:N47) -> 95000
C80: 7. РАБОТЫ — отдельной статьёй | G80: =SUM(G49:G71) -> 125600 | I80: =SUM(I49:I71) -> 235100 | K80: =SUM(K49:K71) -> 420200 | N80: =SUM(N49:N71) -> 235100
C81: МАТЕРИАЛЫ + ПОТОЛОК + ОБОИ + ДВЕРИ (разделы 1–6) | G81: =SUM(G74:G79) -> 232190 | I81: =SUM(I74:I79) -> 598460 | K81: =SUM(K74:K79) -> 1413650 | N81: =SUM(N74:N79) -> 598460
C82: РАБОТЫ (раздел 7) | G82: =G80 -> 125600 | I82: =I80 -> 235100 | K82: =K80 -> 420200 | N82: =N80 -> 235100
C83: ВСЕГО БЕЗ РЕЗЕРВА | G83: =SUM(G74:G80) -> 357790 | I83: =SUM(I74:I80) -> 833560 | K83: =SUM(K74:K80) -> 1833850 | N83: =SUM(N74:N80) -> 833560
C84: Резерв на непредвиденное | E84: =Параметры!$B$18 -> 0.1 | G84: =G83*$E$84 -> 35779 | I84: =I83*$E$84 -> 83356 | K84: =K83*$E$84 -> 183385 | N84: =N83*$E$84 -> 83356
C85: ИТОГО С РЕЗЕРВОМ | G85: =G83+G84 -> 393569 | I85: =I83+I84 -> 916916 | K85: =K83+K84 -> 2017235 | N85: =N83+N84 -> 916916
C86: Стоимость 1 м² квартиры (с резервом) | G86: =IF(Параметры!$B$4=0,0,G85/Параметры!$B$4) -> 7142.8131 | I86: =IF(Параметры!$B$4=0,0,I85/Параметры!$B$4) -> 16640.944 | K86: =IF(Параметры!$B$4=0,0,K85/Параметры!$B$4) -> 36610.436 | N86: =IF(Параметры!$B$4=0,0,N85/Параметры!$B$4) -> 16640.944
C88: Входная дверь стоит — не считаем. Кухня, мебель, техника — на листе 2_Заезд. Не учтено: демонтаж/перенос стен (по заметке брата уже сделано), окна, лоджия, стояки.

Sheet 2_Заезд
A1: 2. ЧТОБЫ ЗАЕХАТЬ: КУХНЯ, СПАЛЬНЯ, ДЕТСКАЯ, ЗАЛ, ПРИХОЖАЯ, ТЕХНИКА — 3 ОПЦИИ
A2: Цены (F, H, J) и количество (E) — синие, правьте. Ссылки — столбец M. Столбец N «Выбор РЕАЛ» — выпадающий список МИН/СРЕД/МАКС, столбец O — сумма реалистичной сборки.
A4: № | B4: Раздел | C4: Позиция | D4: Ед. | E4: Кол-во | F4: Цена МИН | G4: Сумма МИН | H4: Цена СРЕД | I4: Сумма СРЕД | J4: Цена МАКС | K4: Сумма МАКС | L4: Примечание | M4: Где купить | N4: Выбор РЕАЛ | O4: Сумма РЕАЛ
A5: К. КУХНЯ
A6: 1 | B6: Кухня | C6: Кухонный гарнитур | D6: компл | E6: 1 | F6: 70000 | G6: =E6*F6 -> 70000 | H6: 150000 | I6: =E6*H6 -> 150000 | J6: 450000 | K6: =E6*J6 -> 450000 | L6: МИН: модульная Hoff «Амика»/«Барселона» 2.4–3 м или Лемана Delinia · СРЕД: Hoff на заказ (студия планирования в Happy Молл, Саратов) / Лемана на заказ, ЛДСП+МДФ-плёнка · МАКС: фабрика «Мария» | M6: https://hoff.ru/catalog/kukhonnye-garnitury/modulnye-kukhonnye-garnitury/ | N6: МИН | O6: =IF(N6="МИН",G6,IF(N6="МАКС",K6,I6)) -> 70000
A7: 2 | B7: Кухня | C7: Столешница | D7: компл | E7: 1 | F7: 8000 | G7: =E7*F7 -> 8000 | H7: 20000 | I7: =E7*H7 -> 20000 | J7: 90000 | K7: =E7*J7 -> 90000 | L7: МИН: ЛДСП 28 мм Лемана/Hoff · СРЕД: ЛДСП 38 мм / компакт-плита · МАКС: кварцевый агломерат | M7: https://hoff.ru/catalog/kuhnya/kuhonnye_garnitury/ | N7: МИН | O7: =IF(N7="МИН",G7,IF(N7="МАКС",K7,I7)) -> 8000
A8: 3 | B8: Кухня | C8: Фартук (плитка / стекло / компакт) | D8: компл | E8: 1 | F8: 5000 | G8: =E8*F8 -> 5000 | H8: 15000 | I8: =E8*H8 -> 15000 | J8: 35000 | K8: =E8*J8 -> 35000 | L8: по видео стена кухни без фартука | M8: https://saratov.lemanapro.ru/ | N8: СРЕД | O8: =IF(N8="МИН",G8,IF(N8="МАКС",K8,I8)) -> 15000
A9: 4 | B9: Кухня | C9: Мойка + смеситель | D9: компл | E9: 1 | F9: 6000 | G9: =E9*F9 -> 6000 | H9: 18000 | I9: =E9*H9 -> 18000 | J9: 45000 | K9: =E9*J9 -> 45000 | L9: МИН: нерж. накладная · СРЕД: врезная гранит + Lemark · МАКС: Blanco/Omoikiri + Grohe | M9: https://saratov.lemanapro.ru/ | N9: СРЕД | O9: =IF(N9="МИН",G9,IF(N9="МАКС",K9,I9)) -> 18000
A10: 5 | B10: Кухня | C10: Варочная панель электрическая (индукция) | D10: шт | E10: 1 | F10: 12000 | G10: =E10*F10 -> 12000 | H10: 30000 | I10: =E10*H10 -> 30000 | J10: 70000 | K10: =E10*J10 -> 70000 | L10: МИН: Hansa/Weissgauff стеклокерамика · СРЕД: Bosch/Electrolux индукция · МАКС: Bosch Serie 8 / Miele. Нужна отдельная линия 32А — учтена на листе 1_Ремонт | M10: https://www.dns-shop.ru/?city=saratov | N10: СРЕД | O10: =IF(N10="МИН",G10,IF(N10="МАКС",K10,I10)) -> 30000
A11: 6 | B11: Кухня | C11: Духовой шкаф | D11: шт | E11: 1 | F11: 20000 | G11: =E11*F11 -> 20000 | H11: 40000 | I11: =E11*H11 -> 40000 | J11: 90000 | K11: =E11*J11 -> 90000 | M11: https://www.dns-shop.ru/?city=saratov | N11: МИН | O11: =IF(N11="МИН",G11,IF(N11="МАКС",K11,I11)) -> 20000
A12: 7 | B12: Кухня | C12: Вытяжка | D12: шт | E12: 1 | F12: 5000 | G12: =E12*F12 -> 5000 | H12: 15000 | I12: =E12*H12 -> 15000 | J12: 40000 | K12: =E12*J12 -> 40000 | M12: https://www.dns-shop.ru/?city=saratov | N12: МИН | O12: =IF(N12="МИН",G12,IF(N12="МАКС",K12,I12)) -> 5000
A13: 8 | B13: Кухня | C13: Холодильник | D13: шт | E13: 1 | F13: 35000 | G13: =E13*F13 -> 35000 | H13: 70000 | I13: =E13*H13 -> 70000 | J13: 180000 | K13: =E13*J13 -> 180000 | L13: МИН: Indesit/Atlant · СРЕД: Haier/LG NoFrost · МАКС: Bosch/Liebherr | M13: https://www.dns-shop.ru/?city=saratov | N13: СРЕД | O13: =IF(N13="МИН",G13,IF(N13="МАКС",K13,I13)) -> 70000
A14: 9 | B14: Кухня | C14: Посудомоечная машина | D14: шт | E14: 1 | F14: 0 | G14: =E14*F14 -> 0 | H14: 35000 | I14: =E14*H14 -> 35000 | J14: 80000 | K14: =E14*J14 -> 80000 | L14: в МИН не берём | M14: https://www.dns-shop.ru/?city=saratov | N14: СРЕД | O14: =IF(N14="МИН",G14,IF(N14="МАКС",K14,I14)) -> 35000
A15: 10 | B15: Кухня | C15: Микроволновка | D15: шт | E15: 1 | F15: 6000 | G15: =E15*F15 -> 6000 | H15: 12000 | I15: =E15*H15 -> 12000 | J15: 30000 | K15: =E15*J15 -> 30000 | M15: https://www.dns-shop.ru/?city=saratov | N15: МИН | O15: =IF(N15="МИН",G15,IF(N15="МАКС",K15,I15)) -> 6000
A16: 11 | B16: Кухня | C16: Обеденный стол + стулья (4 шт) | D16: компл | E16: 1 | F16: 12000 | G16: =E16*F16 -> 12000 | H16: 35000 | I16: =E16*H16 -> 35000 | J16: 100000 | K16: =E16*J16 -> 100000 | L16: Hoff Саратов — Happy Молл, Вольский тракт 2 | M16: https://hoff.ru/catalog/mebel/ | N16: МИН | O16: =IF(N16="МИН",G16,IF(N16="МАКС",K16,I16)) -> 12000
A17: 12 | B17: Кухня | C17: Посуда, кухонная утварь, текстиль | D17: компл | E17: 1 | F17: 8000 | G17: =E17*F17 -> 8000 | H17: 20000 | I17: =E17*H17 -> 20000 | J17: 50000 | K17: =E17*J17 -> 50000 | M17: https://hoff.ru/catalog/mebel/ | N17: МИН | O17: =IF(N17="МИН",G17,IF(N17="МАКС",K17,I17)) -> 8000
A18: С. СПАЛЬНЯ
A19: 13 | B19: Спальня | C19: Кровать 160×200 с основанием | D19: шт | E19: 1 | F19: 15000 | G19: =E19*F19 -> 15000 | H19: 40000 | I19: =E19*H19 -> 40000 | J19: 120000 | K19: =E19*J19 -> 120000 | L19: МИН: Hoff/Шатура ЛДСП · СРЕД: мягкое изголовье, подъёмный механизм · МАКС: Аскона/массив | M19: https://hoff.ru/catalog/mebel/ | N19: МИН | O19: =IF(N19="МИН",G19,IF(N19="МАКС",K19,I19)) -> 15000
A20: 14 | B20: Спальня | C20: Матрас 160×200 | D20: шт | E20: 1 | F20: 12000 | G20: =E20*F20 -> 12000 | H20: 30000 | I20: =E20*H20 -> 30000 | J20: 80000 | K20: =E20*J20 -> 80000 | L20: МИН: пружинный · СРЕД: независимые пружины Аскона · МАКС: ортопедический премиум | M20: https://hoff.ru/catalog/mebel/ | N20: СРЕД | O20: =IF(N20="МИН",G20,IF(N20="МАКС",K20,I20)) -> 30000
A21: 15 | B21: Спальня | C21: Шкаф для одежды | D21: шт | E21: 1 | F21: 20000 | G21: =E21*F21 -> 20000 | H21: 60000 | I21: =E21*H21 -> 60000 | J21: 180000 | K21: =E21*J21 -> 180000 | L21: МИН: распашной ЛДСП · СРЕД: купе 2 м · МАКС: встроенный на заказ | M21: https://hoff.ru/catalog/mebel/ | N21: МИН | O21: =IF(N21="МИН",G21,IF(N21="МАКС",K21,I21)) -> 20000
A22: 16 | B22: Спальня | C22: Прикроватные тумбы | D22: шт | E22: 2 | F22: 3000 | G22: =E22*F22 -> 6000 | H22: 8000 | I22: =E22*H22 -> 16000 | J22: 25000 | K22: =E22*J22 -> 50000 | M22: https://hoff.ru/catalog/mebel/ | N22: МИН | O22: =IF(N22="МИН",G22,IF(N22="МАКС",K22,I22)) -> 6000
A23: 17 | B23: Спальня | C23: Комод | D23: шт | E23: 1 | F23: 8000 | G23: =E23*F23 -> 8000 | H23: 20000 | I23: =E23*H23 -> 20000 | J23: 50000 | K23: =E23*J23 -> 50000 | M23: https://hoff.ru/catalog/mebel/ | N23: МИН | O23: =IF(N23="МИН",G23,IF(N23="МАКС",K23,I23)) -> 8000
A24: 18 | B24: Спальня | C24: Шторы + карниз | D24: компл | E24: 1 | F24: 5000 | G24: =E24*F24 -> 5000 | H24: 15000 | I24: =E24*H24 -> 15000 | J24: 40000 | K24: =E24*J24 -> 40000 | L24: СРЕД/МАКС — под скрытый карниз в потолке (см. лист 1_Ремонт) | M24: https://hoff.ru/catalog/mebel/ | N24: МИН | O24: =IF(N24="МИН",G24,IF(N24="МАКС",K24,I24)) -> 5000
A25: 19 | B25: Спальня | C25: Постельное, подушки, одеяло | D25: компл | E25: 1 | F25: 5000 | G25: =E25*F25 -> 5000 | H25: 12000 | I25: =E25*H25 -> 12000 | J25: 30000 | K25: =E25*J25 -> 30000 | M25: https://hoff.ru/catalog/mebel/ | N25: МИН | O25: =IF(N25="МИН",G25,IF(N25="МАКС",K25,I25)) -> 5000
A26: 20 | B26: Спальня | C26: Бра / настольные светильники | D26: компл | E26: 1 | F26: 2000 | G26: =E26*F26 -> 2000 | H26: 8000 | I26: =E26*H26 -> 8000 | J26: 25000 | K26: =E26*J26 -> 25000 | M26: https://saratov.lemanapro.ru/ | N26: МИН | O26: =IF(N26="МИН",G26,IF(N26="МАКС",K26,I26)) -> 2000
A27: Д. ДЕТСКАЯ
A28: 21 | B28: Детская | C28: Кровать раздвижная (растущая) 80×130→190 | D28: шт | E28: 1 | F28: 12000 | G28: =E28*F28 -> 12000 | H28: 35000 | I28: =E28*H28 -> 35000 | J28: 90000 | K28: =E28*J28 -> 90000 | L28: МИН: раздвижная ЛДСП Hoff/Шатура · СРЕД: с ящиками и мягким изголовьем (Аскона/Hoff) · МАКС: на заказ / массив. Матрас — тоже раздвижной/секционный | M28: https://hoff.ru/catalog/mebel/ | N28: СРЕД | O28: =IF(N28="МИН",G28,IF(N28="МАКС",K28,I28)) -> 35000
A29: 22 | B29: Детская | C29: Матрас для раздвижной кровати (секционный) | D29: шт | E29: 1 | F29: 7000 | G29: =E29*F29 -> 7000 | H29: 18000 | I29: =E29*H29 -> 18000 | J29: 45000 | K29: =E29*J29 -> 45000 | L29: секции 80×130 + 80×60 или два матраса | M29: https://hoff.ru/catalog/mebel/ | N29: СРЕД | O29: =IF(N29="МИН",G29,IF(N29="МАКС",K29,I29)) -> 18000
A30: 23 | B30: Детская | C30: Письменный стол + стул | D30: компл | E30: 1 | F30: 8000 | G30: =E30*F30 -> 8000 | H30: 25000 | I30: =E30*H30 -> 25000 | J30: 60000 | K30: =E30*J30 -> 60000 | L30: СРЕД/МАКС — растущий стол, ортопедический стул | M30: https://hoff.ru/catalog/mebel/ | N30: СРЕД | O30: =IF(N30="МИН",G30,IF(N30="МАКС",K30,I30)) -> 25000
A31: 24 | B31: Детская | C31: Шкаф | D31: шт | E31: 1 | F31: 15000 | G31: =E31*F31 -> 15000 | H31: 40000 | I31: =E31*H31 -> 40000 | J31: 120000 | K31: =E31*J31 -> 120000 | M31: https://hoff.ru/catalog/mebel/ | N31: МИН | O31: =IF(N31="МИН",G31,IF(N31="МАКС",K31,I31)) -> 15000
A32: 25 | B32: Детская | C32: Стеллаж / полки | D32: шт | E32: 1 | F32: 5000 | G32: =E32*F32 -> 5000 | H32: 15000 | I32: =E32*H32 -> 15000 | J32: 40000 | K32: =E32*J32 -> 40000 | M32: https://hoff.ru/catalog/mebel/ | N32: МИН | O32: =IF(N32="МИН",G32,IF(N32="МАКС",K32,I32)) -> 5000
A33: 26 | B33: Детская | C33: Шторы + карниз | D33: компл | E33: 1 | F33: 4000 | G33: =E33*F33 -> 4000 | H33: 12000 | I33: =E33*H33 -> 12000 | J33: 30000 | K33: =E33*J33 -> 30000 | M33: https://hoff.ru/catalog/mebel/ | N33: МИН | O33: =IF(N33="МИН",G33,IF(N33="МАКС",K33,I33)) -> 4000
A34: 27 | B34: Детская | C34: Ковёр | D34: шт | E34: 1 | F34: 3000 | G34: =E34*F34 -> 3000 | H34: 10000 | I34: =E34*H34 -> 10000 | J34: 30000 | K34: =E34*J34 -> 30000 | M34: https://hoff.ru/catalog/mebel/ | N34: МИН | O34: =IF(N34="МИН",G34,IF(N34="МАКС",K34,I34)) -> 3000
A35: 28 | B35: Детская | C35: Текстиль (постельное, подушки) | D35: компл | E35: 1 | F35: 3000 | G35: =E35*F35 -> 3000 | H35: 8000 | I35: =E35*H35 -> 8000 | J35: 20000 | K35: =E35*J35 -> 20000 | M35: https://hoff.ru/catalog/mebel/ | N35: МИН | O35: =IF(N35="МИН",G35,IF(N35="МАКС",K35,I35)) -> 3000
A36: 29 | B36: Детская | C36: Освещение (настольная лампа, ночник) | D36: компл | E36: 1 | F36: 2000 | G36: =E36*F36 -> 2000 | H36: 6000 | I36: =E36*H36 -> 6000 | J36: 15000 | K36: =E36*J36 -> 15000 | M36: https://saratov.lemanapro.ru/ | N36: МИН | O36: =IF(N36="МИН",G36,IF(N36="МАКС",K36,I36)) -> 2000
A37: З. ЗАЛ
A38: 30 | B38: Зал | C38: Диван | D38: шт | E38: 1 | F38: 25000 | G38: =E38*F38 -> 25000 | H38: 70000 | I38: =E38*H38 -> 70000 | J38: 200000 | K38: =E38*J38 -> 200000 | L38: МИН: прямой еврокнижка · СРЕД: угловой с независимым пружинным блоком · МАКС: модульный, ткань antiklaw | M38: https://hoff.ru/catalog/gostinaya/divany/ | N38: СРЕД | O38: =IF(N38="МИН",G38,IF(N38="МАКС",K38,I38)) -> 70000
A39: 31 | B39: Зал | C39: Телевизор | D39: шт | E39: 1 | F39: 25000 | G39: =E39*F39 -> 25000 | H39: 55000 | I39: =E39*H39 -> 55000 | J39: 150000 | K39: =E39*J39 -> 150000 | L39: МИН: 43–50" 4K (Haier/Xiaomi) · СРЕД: 55" 4K (Samsung/LG) · МАКС: 65–75" OLED/QLED | M39: https://www.dns-shop.ru/catalog/17a8ae1316404e77/televizory-i-aksessuary/ | N39: СРЕД | O39: =IF(N39="МИН",G39,IF(N39="МАКС",K39,I39)) -> 55000
A40: 32 | B40: Зал | C40: Кронштейн / ТВ-тумба | D40: компл | E40: 1 | F40: 3000 | G40: =E40*F40 -> 3000 | H40: 15000 | I40: =E40*H40 -> 15000 | J40: 50000 | K40: =E40*J40 -> 50000 | L40: закладная под кронштейн — в стену, не в потолок | M40: https://hoff.ru/catalog/mebel/ | N40: МИН | O40: =IF(N40="МИН",G40,IF(N40="МАКС",K40,I40)) -> 3000
A41: 33 | B41: Зал | C41: Журнальный стол | D41: шт | E41: 1 | F41: 3000 | G41: =E41*F41 -> 3000 | H41: 12000 | I41: =E41*H41 -> 12000 | J41: 40000 | K41: =E41*J41 -> 40000 | M41: https://hoff.ru/catalog/mebel/ | N41: МИН | O41: =IF(N41="МИН",G41,IF(N41="МАКС",K41,I41)) -> 3000
A42: 34 | B42: Зал | C42: Стеллаж / шкаф / стенка | D42: шт | E42: 1 | F42: 10000 | G42: =E42*F42 -> 10000 | H42: 35000 | I42: =E42*H42 -> 35000 | J42: 120000 | K42: =E42*J42 -> 120000 | M42: https://hoff.ru/catalog/mebel/ | N42: МИН | O42: =IF(N42="МИН",G42,IF(N42="МАКС",K42,I42)) -> 10000
A43: 35 | B43: Зал | C43: Кресло | D43: шт | E43: 1 | F43: 0 | G43: =E43*F43 -> 0 | H43: 20000 | I43: =E43*H43 -> 20000 | J43: 60000 | K43: =E43*J43 -> 60000 | L43: в МИН не берём | M43: https://hoff.ru/catalog/mebel/ | N43: МИН | O43: =IF(N43="МИН",G43,IF(N43="МАКС",K43,I43)) -> 0
A44: 36 | B44: Зал | C44: Ковёр | D44: шт | E44: 1 | F44: 5000 | G44: =E44*F44 -> 5000 | H44: 15000 | I44: =E44*H44 -> 15000 | J44: 50000 | K44: =E44*J44 -> 50000 | M44: https://hoff.ru/catalog/mebel/ | N44: МИН | O44: =IF(N44="МИН",G44,IF(N44="МАКС",K44,I44)) -> 5000
A45: 37 | B45: Зал | C45: Шторы + карниз | D45: компл | E45: 1 | F45: 6000 | G45: =E45*F45 -> 6000 | H45: 18000 | I45: =E45*H45 -> 18000 | J45: 50000 | K45: =E45*J45 -> 50000 | M45: https://hoff.ru/catalog/mebel/ | N45: МИН | O45: =IF(N45="МИН",G45,IF(N45="МАКС",K45,I45)) -> 6000
A46: 38 | B46: Зал | C46: Торшер / бра | D46: компл | E46: 1 | F46: 2000 | G46: =E46*F46 -> 2000 | H46: 8000 | I46: =E46*H46 -> 8000 | J46: 25000 | K46: =E46*J46 -> 25000 | M46: https://saratov.lemanapro.ru/ | N46: МИН | O46: =IF(N46="МИН",G46,IF(N46="МАКС",K46,I46)) -> 2000
A47: П. ПРИХОЖАЯ И ОБЩЕЕ
A48: 39 | B48: Прихожая | C48: Шкаф / вешалка + обувница | D48: компл | E48: 1 | F48: 8000 | G48: =E48*F48 -> 8000 | H48: 30000 | I48: =E48*H48 -> 30000 | J48: 90000 | K48: =E48*J48 -> 90000 | L48: МАКС — встроенный на заказ | M48: https://hoff.ru/catalog/mebel/ | N48: МИН | O48: =IF(N48="МИН",G48,IF(N48="МАКС",K48,I48)) -> 8000
A49: 40 | B49: Прихожая | C49: Зеркало | D49: шт | E49: 1 | F49: 1500 | G49: =E49*F49 -> 1500 | H49: 5000 | I49: =E49*H49 -> 5000 | J49: 15000 | K49: =E49*J49 -> 15000 | M49: https://hoff.ru/catalog/mebel/ | N49: МИН | O49: =IF(N49="МИН",G49,IF(N49="МАКС",K49,I49)) -> 1500
A50: 41 | B50: Общее | C50: Стиральная машина | D50: шт | E50: 1 | F50: 25000 | G50: =E50*F50 -> 25000 | H50: 45000 | I50: =E50*H50 -> 45000 | J50: 100000 | K50: =E50*J50 -> 100000 | L50: место — санузел №1 или кухня; нужен вывод воды и розетка | M50: https://www.dns-shop.ru/?city=saratov | N50: СРЕД | O50: =IF(N50="МИН",G50,IF(N50="МАКС",K50,I50)) -> 45000
A51: 42 | B51: Общее | C51: Пылесос | D51: шт | E51: 1 | F51: 8000 | G51: =E51*F51 -> 8000 | H51: 25000 | I51: =E51*H51 -> 25000 | J51: 60000 | K51: =E51*J51 -> 60000 | L51: МАКС — робот + вертикальный | M51: https://www.dns-shop.ru/?city=saratov | N51: МИН | O51: =IF(N51="МИН",G51,IF(N51="МАКС",K51,I51)) -> 8000
A52: 43 | B52: Общее | C52: Роутер / интернет-подключение | D52: компл | E52: 1 | F52: 3000 | G52: =E52*F52 -> 3000 | H52: 6000 | I52: =E52*H52 -> 6000 | J52: 12000 | K52: =E52*J52 -> 12000 | M52: https://www.dns-shop.ru/?city=saratov | N52: МИН | O52: =IF(N52="МИН",G52,IF(N52="МАКС",K52,I52)) -> 3000
A53: 44 | B53: Общее | C53: Полотенца, коврики в санузлы | D53: компл | E53: 1 | F53: 3000 | G53: =E53*F53 -> 3000 | H53: 8000 | I53: =E53*H53 -> 8000 | J53: 20000 | K53: =E53*J53 -> 20000 | M53: https://hoff.ru/catalog/mebel/ | N53: МИН | O53: =IF(N53="МИН",G53,IF(N53="МАКС",K53,I53)) -> 3000
A54: 45 | B54: Общее | C54: Утюг, гладильная доска, сушилка | D54: компл | E54: 1 | F54: 5000 | G54: =E54*F54 -> 5000 | H54: 10000 | I54: =E54*H54 -> 10000 | J54: 25000 | K54: =E54*J54 -> 25000 | M54: https://www.dns-shop.ru/?city=saratov | N54: МИН | O54: =IF(N54="МИН",G54,IF(N54="МАКС",K54,I54)) -> 5000
A55: Р. РАБОТЫ ПО ОБУСТРОЙСТВУ — отдельной статьёй
A56: 46 | B56: Работы | C56: Сборка и установка кухни, подключение техники | D56: компл | E56: 1 | F56: 8000 | G56: =E56*F56 -> 8000 | H56: 25000 | I56: =E56*H56 -> 25000 | J56: 50000 | K56: =E56*J56 -> 50000 | L56: у «Марии» и при заказе на фабрике часто входит в цену — уточнить | N56: СРЕД | O56: =IF(N56="МИН",G56,IF(N56="МАКС",K56,I56)) -> 25000
A57: 47 | B57: Работы | C57: Сборка мебели (кровати, шкафы, детская, зал) | D57: компл | E57: 1 | F57: 5000 | G57: =E57*F57 -> 5000 | H57: 15000 | I57: =E57*H57 -> 15000 | J57: 30000 | K57: =E57*J57 -> 30000 | L57: Hoff: сборка от 899 ₽ за единицу | N57: СРЕД | O57: =IF(N57="МИН",G57,IF(N57="МАКС",K57,I57)) -> 15000
A58: 48 | B58: Работы | C58: Навес карнизов, кронштейна ТВ, зеркал, полок | D58: компл | E58: 1 | F58: 3000 | G58: =E58*F58 -> 3000 | H58: 8000 | I58: =E58*H58 -> 8000 | J58: 15000 | K58: =E58*J58 -> 15000 | N58: СРЕД | O58: =IF(N58="МИН",G58,IF(N58="МАКС",K58,I58)) -> 8000
A59: 49 | B59: Работы | C59: Подключение стиральной машины | D59: шт | E59: 1 | F59: 1500 | G59: =E59*F59 -> 1500 | H59: 2500 | I59: =E59*H59 -> 2500 | J59: 4000 | K59: =E59*J59 -> 4000 | N59: СРЕД | O59: =IF(N59="МИН",G59,IF(N59="МАКС",K59,I59)) -> 2500
A60: 50 | B60: Работы | C60: Доставка и подъём мебели и техники | D60: компл | E60: 1 | F60: 5000 | G60: =E60*F60 -> 5000 | H60: 15000 | I60: =E60*H60 -> 15000 | J60: 30000 | K60: =E60*J60 -> 30000 | N60: СРЕД | O60: =IF(N60="МИН",G60,IF(N60="МАКС",K60,I60)) -> 15000
C62: ИТОГИ ПО РАЗДЕЛАМ
C63: К. КУХНЯ | G63: =SUM(G6:G17) -> 187000 | I63: =SUM(I6:I17) -> 460000 | K63: =SUM(K6:K17) -> 1260000 | O63: =SUM(O6:O17) -> 297000
C64: С. СПАЛЬНЯ | G64: =SUM(G19:G26) -> 73000 | I64: =SUM(I19:I26) -> 201000 | K64: =SUM(K19:K26) -> 575000 | O64: =SUM(O19:O26) -> 91000
C65: Д. ДЕТСКАЯ | G65: =SUM(G28:G36) -> 59000 | I65: =SUM(I28:I36) -> 169000 | K65: =SUM(K28:K36) -> 450000 | O65: =SUM(O28:O36) -> 110000
C66: З. ЗАЛ | G66: =SUM(G38:G46) -> 79000 | I66: =SUM(I38:I46) -> 248000 | K66: =SUM(K38:K46) -> 745000 | O66: =SUM(O38:O46) -> 154000
C67: П. ПРИХОЖАЯ И ОБЩЕЕ | G67: =SUM(G48:G54) -> 53500 | I67: =SUM(I48:I54) -> 129000 | K67: =SUM(K48:K54) -> 322000 | O67: =SUM(O48:O54) -> 73500
C68: Р. РАБОТЫ ПО ОБУСТРОЙСТВУ — отдельной статьёй | G68: =SUM(G56:G60) -> 22500 | I68: =SUM(I56:I60) -> 65500 | K68: =SUM(K56:K60) -> 129000 | O68: =SUM(O56:O60) -> 65500
C69: ЗАКУПКА (мебель, техника, текстиль) | G69: =SUM(G63:G67) -> 451500 | I69: =SUM(I63:I67) -> 1207000 | K69: =SUM(K63:K67) -> 3352000 | O69: =SUM(O63:O67) -> 725500
C70: РАБОТЫ ПО ОБУСТРОЙСТВУ | G70: =G68 -> 22500 | I70: =I68 -> 65500 | K70: =K68 -> 129000 | O70: =O68 -> 65500
C71: ВСЕГО БЕЗ РЕЗЕРВА | G71: =G69+G70 -> 474000 | I71: =I69+I70 -> 1272500 | K71: =K69+K70 -> 3481000 | O71: =O69+O70 -> 791000
C72: Резерв на непредвиденное | E72: =Параметры!$B$18 -> 0.1 | G72: =G71*$E$72 -> 47400 | I72: =I71*$E$72 -> 127250 | K72: =K71*$E$72 -> 348100 | O72: =O71*$E$72 -> 79100
C73: ИТОГО С РЕЗЕРВОМ | G73: =G71+G72 -> 521400 | I73: =I71+I72 -> 1399750 | K73: =K71+K72 -> 3829100 | O73: =O71+O72 -> 870100
C75: Допущения: 1 двуспальная кровать, 1 детская кровать (один ребёнок), варочная панель электрическая (индукция), под неё отдельная линия 32А заложена в 1_Ремонт, стиральная машина одна. Кухня «Мария» — саратовская фабрика, базовые компоновки на сайте от ~150 тыс.; шоу-рум и экскурсия на фабрику в Саратове.

Sheet 3_Саммари
A1: 3. САММАРИ: СКОЛЬКО ВСЕГО НУЖНО ДЕНЕГ — квартира 55 м², Саратов
A2: Все цифры — формулы с листов 1_Ремонт и 2_Заезд. Меняйте цены там — здесь пересчитается.
A4: Блок | B4: МИН | C4: СРЕД | D4: МАКС | E4: РЕАЛ (сборка) | F4: Комментарий
A5: 1. РЕМОНТ — материалы (пол, потолок, сантехника, электрика, обои, двери) | B5: ='1_Ремонт'!G81 -> 232190 | C5: ='1_Ремонт'!I81 -> 598460 | D5: ='1_Ремонт'!K81 -> 1413650 | E5: ='1_Ремонт'!N81 -> 598460 | F5: включая натяжной потолок «под ключ»
A6: 1. РЕМОНТ — работы | B6: ='1_Ремонт'!G82 -> 125600 | C6: ='1_Ремонт'!I82 -> 235100 | D6: ='1_Ремонт'!K82 -> 420200 | E6: ='1_Ремонт'!N82 -> 235100
A7: 1. РЕМОНТ — резерв | B7: ='1_Ремонт'!G84 -> 35779 | C7: ='1_Ремонт'!I84 -> 83356 | D7: ='1_Ремонт'!K84 -> 183385 | E7: ='1_Ремонт'!N84 -> 83356 | F7: процент задаётся на листе Параметры
A8: 1. РЕМОНТ — ИТОГО | B8: ='1_Ремонт'!G85 -> 393569 | C8: ='1_Ремонт'!I85 -> 916916 | D8: ='1_Ремонт'!K85 -> 2017235 | E8: ='1_Ремонт'!N85 -> 916916 | F8: лист 1_Ремонт
A10: 2. ЗАЕЗД — закупка (кухня, мебель, техника, текстиль) | B10: ='2_Заезд'!G69 -> 451500 | C10: ='2_Заезд'!I69 -> 1207000 | D10: ='2_Заезд'!K69 -> 3352000 | E10: ='2_Заезд'!O69 -> 725500
A11: 2. ЗАЕЗД — работы (сборка, подключение, доставка) | B11: ='2_Заезд'!G70 -> 22500 | C11: ='2_Заезд'!I70 -> 65500 | D11: ='2_Заезд'!K70 -> 129000 | E11: ='2_Заезд'!O70 -> 65500
A12: 2. ЗАЕЗД — резерв | B12: ='2_Заезд'!G72 -> 47400 | C12: ='2_Заезд'!I72 -> 127250 | D12: ='2_Заезд'!K72 -> 348100 | E12: ='2_Заезд'!O72 -> 79100
A13: 2. ЗАЕЗД — ИТОГО | B13: ='2_Заезд'!G73 -> 521400 | C13: ='2_Заезд'!I73 -> 1399750 | D13: ='2_Заезд'!K73 -> 3829100 | E13: ='2_Заезд'!O73 -> 870100 | F13: лист 2_Заезд
A15: ВСЕГО МАТЕРИАЛЫ + ЗАКУПКА | B15: =B5+B10 -> 683690 | C15: =C5+C10 -> 1805460 | D15: =D5+D10 -> 4765650 | E15: =E5+E10 -> 1323960
A16: ВСЕГО РАБОТЫ | B16: =B6+B11 -> 148100 | C16: =C6+C11 -> 300600 | D16: =D6+D11 -> 549200 | E16: =E6+E11 -> 300600
A17: ВСЕГО РЕЗЕРВ | B17: =B7+B12 -> 83179 | C17: =C7+C12 -> 210606 | D17: =D7+D12 -> 531485 | E17: =E7+E12 -> 162456
A18: ОБЩИЙ ИТОГ: РЕМОНТ + ЗАЕЗД | B18: =B8+B13 -> 914969 | C18: =C8+C13 -> 2316666 | D18: =D8+D13 -> 5846335 | E18: =E8+E13 -> 1787016 | F18: с резервом
A19: На 1 м² квартиры | B19: =IF(Параметры!$B$4=0,0,B18/Параметры!$B$4) -> 16605.608 | C19: =IF(Параметры!$B$4=0,0,C18/Параметры!$B$4) -> 42044.755 | D19: =IF(Параметры!$B$4=0,0,D18/Параметры!$B$4) -> 106104.08 | E19: =IF(Параметры!$B$4=0,0,E18/Параметры!$B$4) -> 32432.232
A20: Доля ремонта в общем итоге | B20: =IF(B18=0,0,B8/B18) -> 0.43014463 | C20: =IF(C18=0,0,C8/C18) -> 0.39579119 | D20: =IF(D18=0,0,D8/D18) -> 0.34504266 | E20: =IF(E18=0,0,E8/E18) -> 0.51309893
A22: РЕАЛ (сборка) — реалистичная колонка: ремонт по СРЕД (обои флизелиновые); заезд — кухня модульная Hoff/Лемана по МИН; холодильник, ПММ, индукция, диван, ТВ, матрасы, детская кровать и стол по СРЕД, остальная мебель и мелкая техника по МИН. Меняется выпадающими списками в столбцах M (1_Ремонт) и N (2_Заезд).
A23: Учтено всё до заезда: ремонт (включая обои, двери, уборку) + кухня, мебель, техника. Входная дверь стоит — не считаем. Не учтено: окна, лоджия, стояки.
A24: Как пользоваться: 1) Параметры — площади и количества; 2) 1_Ремонт и 2_Заезд — цены под выбранные товары и выбор МИН/СРЕД/МАКС для колонки РЕАЛ; 3) закупка по ссылкам с листов Закупка_ссылки и 2_Заезд (столбец M).

Sheet Планировка
A1: ПЛАНИРОВКА ПО ПЛАНУ КВ. 312 (2-комн., 55.1 м²) И ПРАВКИ БРАТА
A3: Помещение | B3: По плану, м² | C3: После правок, м² | D3: Назначение в проекте | E3: Что изменено
A4: Спальня | B4: 11.7 | C4: 11.7 | D4: Спальня родителей + выход на лоджию | E4: —
A5: Гостиная | B5: 13.7 | C5: 12.2 | D5: ДЕТСКАЯ (изолированная комната, широкий проём — двустворчатая дверь) | E5: стена №2 сдвинута в сторону гостиной ≈ на 0.4 м (≈ –1.5 м²); проём №3 расширен
A6: Кухня | B6: 10.3 | C6: 11.8 | D6: Кухня-гостиная: кухня + обеденная зона | E6: стена №1 (кухня–прихожая) снесена; +1.5 м² от гостиной
A7: Прихожая | B7: 11.8 | C7: 11.8 | D7: Прихожая у входа (плитка) + зона зала: диван, ТВ | E7: объединена с кухней в единое пространство ≈ 23.6 м²
A8: Ванная | B8: 2.8 | C8: 2.8 | D8: Душевая с подиумом + раковина (по видео) | E8: ванна заменена на душевой подиум
A9: С/у | B9: 2.1 | C9: 2.1 | D9: Унитаз + раковина + газовая колонка (по видео) | E9: —
A10: Лоджия | B10: 2.7 | C10: 2.7 | D10: Утеплённая — кабинет/хранение | E10: —
A11: Итого без лоджии | B11: =SUM(B4:B9) -> 52.4 | C11: =SUM(C4:C9) -> 52.4
A13: Заметка брата (22.02.26): 1) стены кухня–прихожая не будет; 2) стену гостиной сдвинул к гостиной — кухня больше, потом детская; 3) дверной проём сделал широким, чтобы пространство казалось больше.
A14: Выведенные величины для сметы: ламинат 42 м², потолки 52.4 м², плинтус 50 п.м, обои 120 м², двери 3 стандартных + 1 широкая. Дизайн-концепция по 3 опциям — в отдельном документе Word.

Sheet Закупка_ссылки
A1: ЧТО ИМЕННО КУПИТЬ И ГДЕ — Саратов
A2: Ссылки ведут в каталоги магазинов с доставкой/самовывозом в Саратове. Ищите указанную модель/серию через поиск на сайте — конкретные артикулы и цены меняются, сверяйте перед оплатой.
A4: Позиция | B4: Опция | C4: Что купить (модель / серия) | D4: Ориентир цены | E4: Магазин | F4: Ссылка
A5: Напольное покрытие | B5: МИН | C5: Ламинат 32 кл 8 мм: Kronostar Symbio / Artfloor / Kronostep | D5: 700–850 ₽/м² | E5: Лемана ПРО Саратов | F5: https://saratov.lemanapro.ru/catalogue/laminat/klass-33/
A6: Напольное покрытие | B6: МИН | C6: Альтернатива: Профком Саратов, ламинат 33 кл | D6: от 700 ₽/м² | E6: Профком Саратов | F6: https://www.profkom64.ru/product/napolnie_pokritiya/laminat-33-klass/
A7: Напольное покрытие | B7: СРЕД | C7: Ламинат 33 кл 8–10 мм с фаской, влагостойкий: Egger Home / Tarkett / Kastamonu | D7: 1 000–1 400 ₽/м² | E7: Лемана ПРО Саратов | F7: https://saratov.lemanapro.ru/catalogue/laminat/klass-33/
A8: Напольное покрытие | B8: МАКС | C8: SPC-кварцвинил 43 кл 4–5 мм: Alpine Floor / Aquafloor / Quick-Step Alpha | D8: 1 800–2 800 ₽/м² | E8: Паркет73 Саратов | F8: https://saratov.parket73.ru/spc-laminat/
A9: Напольное покрытие | B9: МАКС | C9: SPC / кварцвинил, большой выбор коллекций | D9: от 1 790 ₽/м² | E9: Олимп Паркета Саратов | F9: https://saratov.olimp-parketa.ru/catalog/kvarc-vinilovyy-laminat/
A10: Подложка, плёнка, плинтус | B10: ВСЕ | C10: Подложка ПЭ 2 мм / XPS 3 мм / пробка; плёнка 200 мкм; плинтус ПВХ / МДФ / дюрополимер — раздел «Напольные покрытия» | D10: см. смету | E10: Лемана ПРО Саратов | F10: https://saratov.lemanapro.ru/
A11: Натяжной потолок | B11: МИН | C11: ПВХ матовый MSD Classic, белый, обычный профиль | D11: 300–450 ₽/м² с монтажом | E11: Потолочные компании Саратова (сравнение 72 фирм) | F11: https://saratov.potolochek.su/prices
A12: Натяжной потолок | B12: МИН/СРЕД | C12: Прайс: MSD от 293 ₽/м², Bauf от 460 ₽/м², Teqtum от 990 ₽/м² | D12: по прайсу | E12: СуперПотолок Саратов | F12: https://superpotolok.ru/ceny/
A13: Натяжной потолок | B13: СРЕД | C13: Полотно Bauf / тканевый + теневой профиль EuroKraab | D13: 800–1 100 ₽/м² | E13: РВС-Сервис Саратов | F13: https://potolki-rvs.ru/ceny
A14: Натяжной потолок | B14: МАКС | C14: Тканевый Descor/Clipso + теневой профиль + световые линии/парящий | D14: 1 500–2 500 ₽/м² | E14: НатПотолокСрт | F14: https://saratov.natpotolok.ru/matovyj-potolok
A15: Светильники | B15: ВСЕ | C15: GX53 (МИН) / точечные LED (СРЕД) / магнитный трек (МАКС) — раздел «Освещение» | D15: см. смету | E15: Лемана ПРО Саратов | F15: https://saratov.lemanapro.ru/
... A43: Щит и автоматы | B43: МАКС | C43: ABB S200 / Hager, дифавтоматы на каждую группу, реле напряжения, УЗИП | D43: 50 000–70 000 ₽ | E43: Электротовары.ру | F43: https://elektro-tovars.ru/catalog/rozetki-vyklyuchateli/schneider-electric-rozetki-vyklyuchateli

Sheet Работы_подрядчики
A1: РАСЦЕНКИ НА РАБОТЫ И ГДЕ ИСКАТЬ МАСТЕРОВ — Саратов
A3: Вид работ | B3: Ориентир цены (Саратов, 2026) | C3: Где искать | D3: Ссылка | E3: Что проверить у мастера
A4: Укладка ламината / SPC | B4: 200–500 ₽/м² (SPC и диагональ дороже) | C4: Profi.ru Саратов | D4: https://profi.ru/geo-saratov/remont/pol/ukladka-laminata/price/ | E4: перепад стяжки ≤ 2 мм на 2 м; ламинат должен отлежаться 48 ч
A5: Укладка ламината — бригада с замером | B5: от 285 ₽/м² | C5: S5R Саратов | D5: https://saratov.s5r.ru/ukladka-laminata | E5: бесплатный замер и смета
A6: Натяжные потолки под ключ | B6: 300–450 ₽/м² МИН; 800–1 100 СРЕД; 1 500+ МАКС | C6: СуперПотолок / РВС-Сервис / НатПотолокСрт | D6: https://superpotolok.ru/ceny/ | E6: обвод труб, углы, закладные — считаются отдельно, требуйте полную смету
A7: Плиточник / сантехник / электрик | B7: плиточники от 800 ₽/м²; сантехника и электрика — по точкам | C7: Profi.ru Саратов | D7: https://profi.ru/geo-saratov/remont/plitochniki/price/ | E7: паспорт проверен, отзывы, гарантия на работы
A8: Установка сантехники | B8: унитаз 2 500–4 000; раковина 2 500–4 000; смеситель душа 2 000–3 500; инсталляция 6 000–9 000 | C8: Profi.ru / Avito Саратов | D8: https://profi.ru/geo-saratov/remont/plitochniki/price/ | E8: опрессовка соединений, чек на материалы
A9: Электромонтаж | B9: розетка/выключатель 250–600 ₽; сборка щита 6 000–25 000; точка света 500–800 ₽ | C9: Profi.ru / Avito Саратов | D9: https://profi.ru/geo-saratov/remont/plitochniki/price/ | E9: схема щита на бумаге, маркировка линий, акт проверки

Sheet Видео_и_порядок
A1: ЧТО ВИДНО НА ВИДЕО И В КАКОМ ПОРЯДКЕ ДЕЛАТЬ
A3: Зона | B3: Состояние по видео | C3: Что делать | D3: Этап
A4: Пол в комнатах, кухне, коридоре у окна | B4: Ровная серая стяжка / наливной пол, чистая, без покрытия | C4: Грунт → плёнка → подложка → ламинат/SPC → плинтус | D4: 3
A5: Пол в прихожей и у санузлов | B5: Уложен крупноформатный керамогранит «под мрамор», швы затёрты | C5: Ничего. Только порожек на стыке с ламинатом | D5: 3
A6: Стены во всех комнатах | B6: Оштукатурены и зашпаклёваны (белые), не окрашены, без обоев | C6: Финиш стен — НЕ в этой смете, но делать ДО пола и ДО натяжного потолка (профиль крепится к готовым стенам) | D6: 1
A7: Потолки везде | B7: Голая плита, по ней открытая проводка и трубы, висящие провода | C7: Закрепить кабель в гофре, поставить закладные под люстры/карнизы → натяжной потолок | D7: 2 → 4
A8: Электрика | B8: Из стен торчат провода в местах розеток/выключателей; на стене санузла №1 — корпус розетки; щита в сборе не видно | C8: Собрать щит, поставить розетки/выключатели, прозвонить | D8: 2 (щит) → 5 (розетки)
A9: Санузел №1 | B9: Стены в плитке «оникс», висит газовая колонка, выводы воды и канализации готовы, стоит старый унитаз без бачка (временный), на полу трап/квадрат плитки, угловая полка | C9: Новый унитаз, раковина с тумбой и смесителем, зеркало, гигиенический душ, люк к колонке, вентилятор | D9: 5
A10: Санузел №2 (душевая) | B10: Душевой подиум с линейным трапом, отделан плиткой «под дерево», 3 полки в нише, выводы под смеситель душа и под раковину, светильник висит на проводе | C10: Смеситель + стойка, стеклянное ограждение, раковина с тумбой, полотенцесушитель, вентилятор | D10: 5
A11: Двери | B11: Межкомнатных дверей нет, проёмы пустые | C11: Двери — НЕ в этой смете; ставить ПОСЛЕ пола (этап 6) | D11: 6
A12: Отопление | B12: Радиатор под окном установлен | C12: Ничего | D12: —
A15: ПОРЯДОК РАБОТ (чтобы не переделывать)
A16: 1. Финиш стен (покраска/обои) — до потолка и до пола.
A17: 2. Электрика: сборка щита, разводка потолочных линий в гофре, закладные под люстры и карнизы. Розетки пока НЕ ставить.
A18: 3. Пол: грунт, плёнка, подложка, ламинат/SPC. Плинтус — после дверей (этап 6) либо сразу, если двери с добором.
A19: 4. Натяжные потолки (замер за 1–2 дня, монтаж 1 день на квартиру). Условие: стены готовы, точки света разведены, t в квартире ≥ +10°C.
A20: 5. Сантехника и электроустановка: унитаз, раковины, смесители, стекло душевой, полотенцесушитель, вентиляторы, розетки/выключатели, светильники.
A21: 6. Двери, плинтус, финальная уборка.
A23: ЧТО ОБЯЗАТЕЛЬНО ПОД НАТЯЖНОЙ ПОТОЛОК
A24: — Весь кабель по потолку в гофре, закреплён клипсами каждые 50 см (на видео он висит свободно).
A25: — Закладные (фанера/платформы) под каждую люстру, трек и под карниз штор — на стойках или брусе.
A26: — Штробы и дыры в потолке заделаны, вентканалы закрыты решётками.
A27: — Стены зашпаклёваны до потолка (профиль крепится к стене на дюбели каждые 10–15 см).
... A29: — В санузлах — только ПВХ (тканевый не любит влагу), обвод труб считается отдельно.

Sheet Ссылки_по_позициям
A1: ССЫЛКИ И БЕНЧМАРК ЦЕН ПО САРАТОВУ — НА КАЖДУЮ ПОЗИЦИЮ СМЕТЫ (МИН / СРЕД / МАКС)
A2: Проверка 11.09.2026: цены и ссылки собраны из каталогов магазинов Саратова и площадок с доставкой в Саратов. «Цена найдена» — то, что реально показано на странице/в поисковой выдаче на дату проверки; «Цена в смете» — из листов 1_Ремонт / 2_Заезд (не менялась). Отклонение > ±30 % выделено. Статус «уточнить» = подтверждённой цены нет, дана ссылка в каталог. Перед оплатой сверяйте цену на сайте. АВИТО: на каждую позицию есть строка «Авито Саратов» (опция ВСЕ) с готовым поиском — через Авито можно посмотреть предложения магазинов и частников по Саратову и оптимизировать стоимость относительно сметы; цены с Авито снимаются вручную (автоматическая проверка недоступна).
A3: Строк: 442 · подтверждено: 217 · уточнить: 225 (в т. ч. 110 ссылок на поиск Авито Саратов — цены снимать вручную)
A5: Лист | B5: № | C5: Раздел | D5: Позиция | E5: Ед. | F5: Опция | G5: Модель / вариант | H5: Цена найдена, ₽ | I5: Цена в смете, ₽ | J5: Отклонение, % | K5: Магазин / источник | L5: Город | M5: Ссылка | N5: Подтверждение | O5: Дата проверки | P5: Статус | Q5: Комментарий
A6: 1_Ремонт | B6: 1 | C6: 1. Пол | D6: Напольное покрытие (ламинат / SPC) | E6: м² | F6: МИН | G6: Ламинат ELEGANTE Дуб Сидамо, 33 кл (Профком) | H6: 591 | I6: 700 | J6: -15.6 | K6: Профком Саратов | L6: Саратов | M6: https://www.profkom64.ru/product/napolnie_pokritiya/laminat-33-klass/ | N6: страница | O6: 2026-09-11 | P6: ок | Q6: Дешевле сметного 32 кл; Floorpan Lagoon 705 ₽/м², Egger 735–746 ₽/м² там же
A7: 1_Ремонт | B7: 1 | C7: 1. Пол | D7: Напольное покрытие (ламинат / SPC) | E7: м² | F7: СРЕД | G7: Ламинат Aberhof Storm 8 мм, 33 кл, фаска V4 | H7: 1060 | I7: 1150 | J7: -7.8 | K7: Профком Саратов | L7: Саратов | M7: https://www.profkom64.ru/product/napolnie_pokritiya/laminat-33-klass/ | N7: страница | O7: 2026-09-11 | P7: ок | Q7: Kastamonu Sunfloor 1094; Aberhof Cruise 10 мм 1342; Tarkett Pilot 10 мм 1845 ₽/м²
A8: 1_Ремонт | B8: 1 | C8: 1. Пол | D8: Напольное покрытие (ламинат / SPC) | E8: м² | F8: МАКС | G8: SPC Akplast Royce Ultima 4,5 мм | H8: 2050 | I8: 2300 | J8: -10.9 | K8: Паркет73 Саратов | L8: Саратов | M8: https://saratov.parket73.ru/spc-laminat/ | N8: страница | O8: 2026-09-11 | P8: ок | Q8: Класс износостойкости на странице не показан; Tarkett Blackwood Stone 4,4 мм 1799; Олимп Паркета Calitex Elementals 2370 ₽/м² (https://saratov.olimp-parketa.ru/catalog/kvarc-vinilovyy-laminat/)
A9: 1_Ремонт | B9: 1 | C9: 1. Пол | D9: Напольное покрытие (ламинат / SPC) | E9: м² | F9: ВСЕ | G9: Авито Саратов — поиск «Напольное покрытие» (новые товары магазинов и объявления) | K9: Авито Саратов | L9: Саратов | M9: https://www.avito.ru/saratov?q=%D0%9D%D0%B0%D0%BF%D0%BE%D0%BB%D1%8C%D0%BD%D0%BE%D0%B5%20%D0%BF%D0%BE%D0%BA%D1%80%D1%8B%D1%82%D0%B8%D0%B5 | N9: не проверено | O9: 2026-09-11 | P9: уточнить | Q9: Через Авито можно посмотреть предложения по Саратову и оптимизировать стоимость: откройте поиск по ссылке, сравните с ценой в смете и с вариантами магазинов выше. Автоматически цены с Авито снять нельзя (доступ по IP ограничен) — смотреть вручную.
A10: 1_Ремонт | B10: 2 | C10: 1. Пол | D10: Подложка | E10: м² | F10: МИН | G10: НПЭ (вспененный ПЭ) 2 мм, рулон шир. 1,05 м | H10: 15.3 | I10: 100 | J10: -84.7 | K10: Профком Саратов | L10: Саратов | M10: https://www.profkom64.ru/product/napolnie_pokritiya/podlozhka_pod_laminat_linoleum_parket/ | N10: страница | O10: 2026-09-11 | P10: ок | Q10: 16,10 ₽/п.м при ширине 1,05 м = 15,3 ₽/м²; смета завышена в 6 раз
A11: 1_Ремонт | B11: 2 | C11: 1. Пол | D11: Подложка | E11: м² | F11: СРЕД | G11: XPS 3 мм (гармошка) / Arbiton | I11: 200 | K11: Профком Саратов | L11: Саратов | M11: https://www.profkom64.ru/product/napolnie_pokritiya/podlozhka_pod_laminat_linoleum_parket/ | N11: не проверено | O11: 2026-09-11 | P11: уточнить | Q11: Гармошка 3 мм 398 ₽/упак — площадь упаковки на странице не указана; Arbiton XPS 3 мм по сниппетам 432–1085 ₽ без подтверждённой единицы; НПЭ 3 мм 24,20 ₽/п.м (=23 ₽/м²)
A12: 1_Ремонт | B12: 2 | C12: 1. Пол | D12: Подложка | E12: м² | F12: МАКС | G12: Пробковая подложка 2 мм, рулон 10×1 м | H12: 413 | I12: 350 | J12: 18 | K12: Профком Саратов | L12: Саратов | M12: https://www.profkom64.ru/product/napolnie_pokritiya/podlozhka_pod_laminat_linoleum_parket/ | N12: страница | O12: 2026-09-11 | P12: ок | Q12: 4 131 ₽/рулон 10 м² = 413 ₽/м²; Solid PROtector Thermo SPC 1 мм 824 ₽/рулон и гармошка SPC/LVT 1,5 мм 862 ₽/упак — площадь не указана
A13: 1_Ремонт | B13: 2 | C13: 1. Пол | D13: Подложка | E13: м² | F13: ВСЕ | G13: Авито Саратов — поиск «Подложка» (новые товары магазинов и объявления) | K13: Авито Саратов | L13: Саратов | M13: https://www.avito.ru/saratov?q=%D0%9F%D0%BE%D0%B4%D0%BB%D0%BE%D0%B6%D0%BA%D0%B0 | N13: не проверено | O13: 2026-09-11 | P13: уточнить | Q13: Через Авито можно посмотреть предложения по Саратову и оптимизировать стоимость: откройте поиск по ссылке, сравните с ценой в смете и с вариантами магазинов выше. Автоматически цены с Авито снять нельзя (доступ по IP ограничен) — смотреть вручную.
A14: 1_Ремонт | B14: 3 | C14: 1. Пол | D14: Плёнка пароизоляция 200 мкм | E14: м² | F14: МИН | G14: Плёнка полиэтиленовая 200 мкм (категория) | H14: 14 | I14: 30 | J14: -53.3 | K14: Бикра-М (Москва) | L14: доставка в Саратов | M14: https://bikra-m.ru/guard/plenka-ograzhdeniya-i-ukrytiya/plenka/200-mkm/ | N14: сниппет | O14: 2026-09-11 | P14: уточнить | Q14: «от 14 ₽/м²» в заголовке; московский поставщик, доставка в Саратов не проверена
A15: 1_Ремонт | B15: 3 | C15: 1. Пол | D15: Плёнка пароизоляция 200 мкм | E15: м² | F15: СРЕД | G15: Плёнка п/э 200 мк прозрачная, рулон 100 м | I15: 40 | K15: Профком Саратов | L15: Саратов | M15: https://www.profkom64.ru/product/utepliteli/paroizol_plenka/plenka_200_prozrachnaya.html | N15: сниппет | O15: 2026-09-11 | P15: уточнить | Q15: 72 ₽/п.м по сниппету; ширина рулона не указана (при рукаве 1,5 м ≈ 24 ₽/м² — допущение)
A16: 1_Ремонт | B16: 3 | C16: 1. Пол | D16: Плёнка пароизоляция 200 мкм | E16: м² | F16: МАКС | G16: Плёнки строительные 200 мкм (категория) | I16: 40 | K16: Лемана ПРО | L16: доставка в Саратов | M16: https://lemanapro.ru/catalogue/plenki-stroitelnye/200-mkm/ | N16: сниппет | O16: 2026-09-11 | P16: уточнить | Q16: Каталог «от 581 ₽» за рулон, размер рулона не указан; саратовский каталог блокирует доступ (401)
A17: 1_Ремонт | B17: 3 | C17: 1. Пол | D17: Плёнка пароизоляция 200 мкм | E17: м² | F17: ВСЕ | G17: Авито Саратов — поиск «Плёнка пароизоляция 200 мкм» (новые товары магазинов и объявления) | K17: Авито Саратов | L17: Саратов | M17: https://www.avito.ru/saratov?q=%D0%9F%D0%BB%D1%91%D0%BD%D0%BA%D0%B0%20%D0%BF%D0%B0%D1%80%D0%BE%D0%B8%D0%B7%D0%BE%D0%BB%D1%8F%D1%86%D0%B8%D1%8F%20200%20%D0%BC%D0%BA%D0%BC | N17: не проверено | O17: 2026-09-11 | P17: уточнить | Q17: Через Авито можно посмотреть предложения по Саратову и оптимизировать стоимость: откройте поиск по ссылке, сравните с ценой в смете и с вариантами магазинов выше. Автоматически цены с Авито снять нельзя (доступ по IP ограничен) — смотреть вручную.
A18: 1_Ремонт | B18: 4 | C18: 1. Пол | D18: Плинтус напольный | E18: п.м | F18: МИН | G18: ПВХ Идеал Комфорт 55 мм с кабель-каналом | H18: 85 | I18: 130 | J18: -34.6 | K18: Профком (Энгельс/Саратов) | L18: Саратов | M18: https://engels.profkom64.ru/product/napolnie_pokritiya/plintus/ | N18: страница | O18: 2026-09-11 | P18: уточнить | Q18: 73–85 ₽/шт; длина хлыста на странице не указана (обычно 2,5 м ≈ 34 ₽/п.м — допущение); заглушки 29–45 ₽/пара
A19: 1_Ремонт | B19: 4 | C19: 1. Пол | D19: Плинтус напольный | E19: п.м | F19: СРЕД | G19: Дюрополимер Decomaster A036 100×16 под покраску | H19: 339 | I19: 350 | J19: -3.1 | K19: Про-плинтус.ру | L19: доставка в Саратов | M19: https://pro-plintys.ru/a036plintusartprofilnapolnyyizdyuropolimerapodpokrasku100x16 | N19: сниппет | O19: 2026-09-11 | P19: ок | Q19: 339 ₽/м (хлыст 2 м); МДФ в Лемана ПРО «от 368 ₽» (единица не указана), polvdome МДФ от 150 ₽/п.м
A20: 1_Ремонт | B20: 4 | C20: 1. Пол | D20: Плинтус напольный | E20: п.м | F20: МАКС | G20: Скрытый (теневой) алюминиевый плинтус | I20: 800 | K20: Лемана ПРО | L20: доставка в Саратов | M20: https://lemanapro.ru/catalogue/napolnye-plintusy/tenevye/ | N20: сниппет | O20: 2026-09-11 | P20: уточнить | Q20: Каталог «от 800 ₽», единица (шт/п.м) не указана; adv-parket теневой «от 560 ₽»; pro-plintus FD-04.1 42×14×2500 без цены в сниппете
A21: 1_Ремонт | B21: 4 | C21: 1. Пол | D21: Плинтус напольный | E21: п.м | F21: ВСЕ | G21: Авито Саратов — поиск «Плинтус напольный» (новые товары магазинов и объявления) | K21: Авито Саратов | L21: Саратов | M21: https://www.avito.ru/saratov?q=%D0%9F%D0%BB%D0%B8%D0%BD%D1%82%D1%83%D1%81%20%D0%BD%D0%B0%D0%BF%D0%BE%D0%BB%D1%8C%D0%BD%D1%8B%D0%B9 | N21: не проверено | O21: 2026-09-11 | P21: уточнить | Q21: Через Авито можно посмотреть предложения по Саратову и оптимизировать стоимость: откройте поиск по ссылке, сравните с ценой в смете и с вариантами магазинов выше. Автоматически цены с Авито снять нельзя (доступ по IP ограничен) — смотреть вручную.
A22: 1_Ремонт | B22: 5 | C22: 1. Пол | D22: Порожки, стыки плитка–ламинат | E22: компл | F22: МИН | G22: 3× порог скрытый Artens 30×900 мм, 0–8 мм | H22: 681 | I22: 1500 | J22: -54.6 | K22: Лемана ПРО (цена Самара) | L22: доставка в Саратов | M22: https://samara.lemanapro.ru/product/porog-raznourovnevyy-kant-artens-skrytyy-17855099/ | N22: сниппет | O22: 2026-09-11 | P22: уточнить | Q22: 227 ₽/шт × 3 стыка (коридор + 2 санузла — допущение); цена в Самаре, Саратов блокирует доступ
A23: 1_Ремонт | B23: 5 | C23: 1. Пол | D23: Порожки, стыки плитка–ламинат | E23: компл | F23: СРЕД | G23: 3× порог разноуровневый алюминиевый ПР06 900×41, закрытый крепёж | H23: 2955 | I23: 3000 | J23: -1.5 | K23: Лемана ПРО (цена Тверь) | L23: доставка в Саратов | M23: https://tver.lemanapro.ru/product/porog-dlya-pola-raznourovnevyy-alyuminievyy-pr06-zakrytyy-krepezh-900x41-perepad-belyy-matovyy-91155692/ | N23: сниппет | O23: 2026-09-11 | P23: уточнить | Q23: 985 ₽/шт × 3; количество стыков — допущение
A24: 1_Ремонт | B24: 5 | C24: 1. Пол | D24: Порожки, стыки плитка–ламинат | E24: компл | F24: МАКС | G24: Т-образный / скрытый порог по размеру, пробковый компенсатор | I24: 6000 | K24: Лемана ПРО | L24: доставка в Саратов | M24: https://lemanapro.ru/catalogue/porozhki-dlya-pola/raznourovnevye/ | N24: не проверено | O24: 2026-09-11 | P24: уточнить | Q24: Цен на заказные порожки не найдено; каталог разноуровневых «от 230 ₽»
A25: 1_Ремонт | B25: 5 | C25: 1. Пол | D25: Порожки, стыки плитка–ламинат | E25: компл | F25: ВСЕ | G25: Авито Саратов — поиск «Порожки, стыки плитка–ламинат» (новые товары магазинов и объявления) | K25: Авито Саратов | L25: Саратов | M25: https://www.avito.ru/saratov?q=%D0%9F%D0%BE%D1%80%D0%BE%D0%B6%D0%BA%D0%B8%2C%20%D1%81%D1%82%D1%8B%D0%BA%D0%B8%20%D0%BF%D0%BB%D0%B8%D1%82%D0%BA%D0%B0%E2%80%93%D0%BB%D0%B0%D0%BC%D0%B8%D0%BD%D0%B0%D1%82 | N25: не проверено | O25: 2026-09-11 | P25: уточнить | Q25: Через Авито можно посмотреть предложения по Саратову и оптимизировать стоимость: откройте поиск по ссылке, сравните с ценой в смете и с вариантами магазинов выше. Автоматически цены с Авито снять нельзя (доступ по IP ограничен) — смотреть вручную.
A26: 1_Ремонт | B26: 6 | C26: 2. Потолок | D26: Натяжной потолок с монтажом «под ключ» | E26: м² | F26: МИН | G26: ПВХ матовый белый HALEAD, обычный профиль, с монтажом | H26: 380 | I26: 400 | J26: -5 | K26: РВС-Сервис Саратов | L26: Саратов | M26: https://potolki-rvs.ru/ceny | N26: страница | O26: 2026-09-11 | P26: ок | Q26: 380 ₽/м² от 30 м² (400 до 18 м²); СуперПотолок MSD «от 293 ₽/м²» (https://superpotolok.ru/ceny/)
A27: 1_Ремонт | B27: 6 | C27: 2. Потолок | D27: Натяжной потолок с монтажом «под ключ» | E27: м² | F27: СРЕД | G27: Bauf (ширина >3,6 м) с монтажом + теневой профиль | H27: 590 | I27: 950 | J27: -37.9 | K27: СуперПотолок Саратов | L27: Саратов | M27: https://superpotolok.ru/ceny/ | N27: страница | O27: 2026-09-11 | P27: уточнить | Q27: 590 ₽/м² только полотно с монтажом (460 до 3,6 м); теневой профиль отдельно: Хоум Комфорт 150–340 ₽/п.м + монтаж 650–1000 ₽/п.м (https://xn--80aagvjfuafcrkii.xn--p1ai/tenevoj-natyazhnoj-potolok/); zabor.bz «теневой от 488 ₽/м²»
A28: 1_Ремонт | B28: 6 | C28: 2. Потолок | D28: Натяжной потолок с монтажом «под ключ» | E28: м² | F28: МАКС | G28: Тканевый Descor D-premium белый с монтажом | H28: 1800 | I28: 1800 | J28: 0 | K28: РВС-Сервис Саратов | L28: Саратов | M28: https://potolki-rvs.ru/ceny | N28: страница | O28: 2026-09-11 | P28: ок | Q28: Descor белый 1500, D-premium 1650–1800 ₽/м²; световые линии/контурная подсветка +900 ₽/п.м, ниша с подсветкой 4200 ₽/п.м; СуперПотолок Descor от 2700 ₽/м²
A29: 1_Ремонт | B29: 6 | C29: 2. Потолок | D29: Натяжной потолок с монтажом «под ключ» | E29: м² | F29: ВСЕ | G29: Авито Саратов — поиск «Натяжной потолок с монтажом «под ключ»» (новые товары магазинов и объявления) | K29: Авито Саратов | L29: Саратов | M29: https://www.avito.ru/saratov?q=%D0%9D%D0%B0%D1%82%D1%8F%D0%B6%D0%BD%D0%BE%D0%B9%20%D0%BF%D0%BE%D1%82%D0%BE%D0%BB%D0%BE%D0%BA%20%D1%81%20%D0%BC%D0%BE%D0%BD%D1%82%D0%B0%D0%B6%D0%BE%D0%BC%20%C2%AB%D0%BF%D0%BE%D0%B4%20%D0%BA%D0%BB%D1%8E%D1%87%C2%BB | N29: не проверено | O29: 2026-09-11 | P29: уточнить | Q29: Через Авито можно посмотреть предложения по Саратову и оптимизировать стоимость: откройте поиск по ссылке, сравните с ценой в смете и с вариантами магазинов выше. Автоматически цены с Авито снять нельзя (доступ по IP ограничен) — смотреть вручную.
A30: 1_Ремонт | B30: 7 | C30: 2. Потолок | D30: Закладные (брус/платформы) под люстры, карнизы | E30: компл | F30: МИН | G30: 2 платформы под люстру (420 ₽) + закладная под карниз 3 м (550 ₽/м) | H30: 2490 | I30: 2000 | J30: 24.5 | K30: РВС-Сервис Саратов | L30: Саратов | M30: https://potolki-rvs.ru/ceny | N30: страница | O30: 2026-09-11 | P30: уточнить | Q30: Состав комплекта — допущение; в прайсе это «установка светильника 420 ₽» и «карниз 550 ₽/м»
A31: 1_Ремонт | B31: 7 | C31: 2. Потолок | D31: Закладные (брус/платформы) под люстры, карнизы | E31: компл | F31: СРЕД | G31: Точка монтажа 550 ₽; встраиваемый светильник до 350 мм 1200 ₽, свыше 1500 ₽ | I31: 4000 | K31: СуперПотолок Саратов | L31: Саратов | M31: https://superpotolok.ru/ceny/ | N31: страница | O31: 2026-09-11 | P31: уточнить | Q31: Закладная под карниз в прайсе не выделена; сумма комплекта не собирается без состава
A32: 1_Ремонт | B32: 7 | C32: 2. Потолок | D32: Закладные (брус/платформы) под люстры, карнизы | E32: компл | F32: МАКС | G32: Усиленные закладные + ниша под карниз | I32: 8000 | K32: РВС-Сервис Саратов | L32: Саратов | M32: https://potolki-rvs.ru/potolki/nisha-pod-karniz.html | N32: не проверено | O32: 2026-09-11 | P32: уточнить | Q32: Отдельной цены нет; ориентир РВС «ниша с подсветкой 4200 ₽/п.м»
A33: 1_Ремонт | B33: 7 | C33: 2. Потолок | D33: Закладные (брус/платформы) под люстры, карнизы | E33: компл | F33: ВСЕ | G33: Авито Саратов — поиск «Закладные под люстры, карнизы» (новые товары магазинов и объявления) | K33: Авито Саратов | L33: Саратов | M33: https://www.avito.ru/saratov?q=%D0%97%D0%B0%D0%BA%D0%BB%D0%B0%D0%B4%D0%BD%D1%8B%D0%B5%20%D0%BF%D0%BE%D0%B4%20%D0%BB%D1%8E%D1%81%D1%82%D1%80%D1%8B%2C%20%D0%BA%D0%B0%D1%80%D0%BD%D0%B8%D0%B7%D1%8B | N33: не проверено | O33: 2026-09-11 | P33: уточнить | Q33: Через Авито можно посмотреть предложения по Саратову и оптимизировать стоимость: откройте поиск по ссылке, сравните с ценой в смете и с вариантами магазинов выше. Автоматически цены с Авито снять нельзя (доступ по IP ограничен) — смотреть вручную.
A34: 1_Ремонт | B34: 8 | C34: 2. Потолок | D34: Кабель ВВГнг-LS + гофра для потолочных линий | E34: компл | F34: МИН | G34: 100 м ВВГнг-LS 3×1,5 (43,5 ₽/м) + 100 м гофра Экопласт D16 (991 ₽) | H34: 5341 | I34: 6000 | J34: -11 | K34: Ламповед + Лемана ПРО (цена Ростов) | L34: доставка в Саратов | M34: https://www.lampoved.ru/kabeli/vvgng/vvgngls315 | N34: сниппет | O34: 2026-09-11 | P34: уточнить | Q34: Метраж 100+100 м — допущение; гофра https://rostov.lemanapro.ru/product/truba-gofrirovannaya-ekoplast-d16-mm-100-m-pvh-legkaya-s-protyazhkoy-cvet-seryy-10056016/
A35: 1_Ремонт | B35: 8 | C35: 2. Потолок | D35: Кабель ВВГнг-LS + гофра для потолочных линий | E35: компл | F35: СРЕД | G35: ВВГнг(А)-LS 3×1,5 уп.100 м Русский Свет (10 302,9 ₽) + гофра DKC D16 100 м (1 798 ₽) | H35: 12101 | I35: 12000 | J35: 0.8 | K35: Русский Свет (rs24) + Лемана ПРО (цена Краснодар) | L35: доставка в Саратов | M35: https://rs24.ru/product/2962068 | N35: сниппет | O35: 2026-09-11 | P35: уточнить | Q35: Метраж — допущение; саратовский МегаVольт (volt64.ru): ВВГнг 3×1,5 (без LS) 90 ₽/м; гофра https://krasnodar.lemanapro.ru/product/truba-gofrirovannaya-dkc-d16-mm-100-m-pvh-legkaya-s-protyazhkoy-cvet-seryy-85174899/
A36: 1_Ремонт | B36: 8 | C36: 2. Потолок | D36: Кабель ВВГнг-LS + гофра для потолочных линий | E36: компл | F36: МАКС | G36: 100 м ВВГнг(А)-LS 3×1,5 Конкорд ЭТМ (104,24 ₽/м) + 2×50 м гофра DKC D25 (2 354 ₽, Лемана Саратов) | H36: 15132 | I36: 20000 | J36: -24.3 | K36: ЭТМ + Лемана ПРО Саратов | L36: Саратов | M36: https://www.etm.ru/cat/nn/9729228 | N36: сниппет | O36: 2026-09-11 | P36: уточнить | Q36: Метраж — допущение; гофра D25 https://saratov.lemanapro.ru/product/truba-gofrirovannaya-s-protyazhkoy-dkc-pvh-d25-mm-50-m-legkaya-cvet-chernyy-91538362/
A37: 1_Ремонт | B37: 8 | C37: 2. Потолок | D37: Кабель ВВГнг-LS + гофра для потолочных линий | E37: компл | F37: ВСЕ | G37: Авито Саратов — поиск «Кабель ВВГнг-LS + гофра для потолочных линий» (новые товары магазинов и объявления) | K37: Авито Саратов | L37: Саратов | M37: https://www.avito.ru/saratov?q=%D0%9A%D0%B0%D0%B1%D0%B5%D0%BB%D1%8C%20%D0%92%D0%92%D0%93%D0%BD%D0%B3-LS%20%2B%20%D0%B3%D0%BE%D1%84%D1%80%D0%B0%20%D0%B4%D0%BB%D1%8F%20%D0%BF%D0%BE%D1%82%D0%BE%D0%BB%D0%BE%D1%87%D0%BD%D1%8B%D1%85%20%D0%BB%D0%B8%D0%BD%D0%B8%D0%B9 | N37: не проверено | O37: 2026-09-11 | P37: уточнить | Q37: Через Авито можно посмотреть предложения по Саратову и оптимизировать стоимость: откройте поиск по ссылке, сравните с ценой в смете и с вариантами магазинов выше. Автоматически цены с Авито снять нельзя (доступ по IP ограничен) — смотреть вручную.
A38: 1_Ремонт | B38: 9 | C38: 2. Потолок | D38: Светильники потолочные | E38: шт | F38: МИН | G38: Накладной Ecola GX53 DGX5318 белый | H38: 82 | I38: 250 | J38: -67.2 | K38: ВсеИнструменты | L38: доставка в Саратов | M38: https://www.vseinstrumenti.ru/electrika-i-svet/svetilniki/nastenno-potolochnye/nakladnye/ecola/gx53-dgx5318-legkij-belyj-svetilnik-18x83-fw53ffecd/ | N38: сниппет | O38: 2026-09-11 | P38: ок | Q38: Без лампы; лампа Uniel GX53 8 Вт 81 ₽ в Лемана Саратов (https://saratov.lemanapro.ru/product/lampa-svetodiodnaya-uniel-gx53-8-vt-670-lm-svet-holodnyy-belyy-18336805/) → 163 ₽ с лампой
A39: 1_Ремонт | B39: 9 | C39: 2. Потолок | D39: Светильники потолочные | E39: шт | F39: СРЕД | G39: Встраиваемый LED Apeyron 06-17, отв. 85 мм | H39: 615 | I39: 700 | J39: -12.1 | K39: Лемана ПРО Саратов | L39: Саратов | M39: https://saratov.lemanapro.ru/product/svetilnik-tochechnyy-svetodiodnyy-vstraivaemyy-apeyron-06-17-pod-otverstie-85-mm-88110327/ | N39: сниппет | O39: 2026-09-11 | P39: ок | Q39: Люстра Семь огней Трине 8 ламп 3 558 ₽ там же (для 2 люстр по смете)
A40: 1_Ремонт | B40: 9 | C40: 2. Потолок | D40: Светильники потолочные | E40: шт | F40: МАКС | G40: Магнитный трековый светильник 48V (Spot ET48 18W и аналоги) | I40: 2500 | K40: Лемана ПРО | L40: доставка в Саратов | M40: https://lemanapro.ru/catalogue/trekovye-sistemy-osveshcheniya/magnitnye-vstraivaemye/ | N40: сниппет | O40: 2026-09-11 | P40: уточнить | Q40: Категория «от 900–988 ₽» без цены конкретной модели; шинопровод и блок питания в смете не выделены
A41: 1_Ремонт | B41: 9 | C41: 2. Потолок | D41: Светильники потолочные | E41: шт | F41: ВСЕ | G41: Авито Саратов — поиск «Светильники потолочные» (новые товары магазинов и объявления) | K41: Авито Саратов | L41: Саратов | M41: https://www.avito.ru/saratov?q=%D0%A1%D0%B2%D0%B5%D1%82%D0%B8%D0%BB%D1%8C%D0%BD%D0%B8%D0%BA%D0%B8%20%D0%BF%D0%BE%D1%82%D0%BE%D0%BB%D0%BE%D1%87%D0%BD%D1%8B%D0%B5 | N41: не проверено | O41: 2026-09-11 | P41: уточнить | Q41: Через Авито можно посмотреть предложения по Саратову и оптимизировать стоимость: откройте поиск по ссылке, сравните с ценой в смете и с вариантами магазинов выше. Автоматически цены с Авито снять нельзя (доступ по IP ограничен) — смотреть вручную.
A42: 1_Ремонт | B42: 10 | C42: 2. Потолок | D42: Ниша ГКЛ под скрытый карниз (материалы) | E42: компл | F42: МИН | G42: Не делаем — карниз накладной | H42: 0 | I42: 0 | K42: — | L42: Саратов | M42: https://www.profkom64.ru/product/gipsokarton/gips-12-5-mm/ | N42: не проверено | O42: 2026-09-11 | P42: ок | Q42: По смете 0
A43: 1_Ремонт | B43: 10 | C43: 2. Потолок | D43: Ниша ГКЛ под скрытый карниз (материалы) | E43: компл | F43: СРЕД | G43: ГКЛ Кнауф 2500×1200×12,5 (392 ₽/лист) + профиль ПП 60×27 + ПН 28×27 + подвесы | I43: 5000 | K43: Профком Саратов | L43: Саратов | M43: https://www.profkom64.ru/product/gipsokarton/gips-12-5-mm/ | N43: страница | O43: 2026-09-11 | P43: уточнить | Q43: ГКЛ Магма 341, Кнауф 392, ГКЛВ Кнауф 529 ₽/лист; ПП 60×27 3 м: 179–235 ₽ (KGSnab, Москва), Knauf 307 ₽ (Лемана Москва); ПН/подвесы/саморезы не найдены — сумма не собирается
A44: 1_Ремонт | B44: 10 | C44: 2. Потолок | D44: Ниша ГКЛ под скрытый карниз (материалы) | E44: компл | F44: МАКС | G44: ГКЛВ Кнауф (529 ₽/лист) + профиль Knauf 0,6 мм (307 ₽/шт) + комплектующие | I44: 12000 | K44: Профком Саратов + Лемана ПРО | L44: Саратов | M44: https://www.profkom64.ru/product/gipsokarton/gips-12-5-mm/ | N44: страница | O44: 2026-09-11 | P44: уточнить | Q44: Состав ниши не задан; профиль https://lemanapro.ru/product/profil-potolochnyy-pp-knauf-06-mm-60x27x3000-mm-12095334/
A45: 1_Ремонт | B45: 10 | C45: 2. Потолок | D45: Ниша ГКЛ под скрытый карниз (материалы) | E45: компл | F45: ВСЕ | G45: Авито Саратов — поиск «Ниша ГКЛ под скрытый карниз» (новые товары магазинов и объявления) | K45: Авито Саратов | L45: Саратов | M45: https://www.avito.ru/saratov?q=%D0%9D%D0%B8%D1%88%D0%B0%20%D0%93%D0%9A%D0%9B%20%D0%BF%D0%BE%D0%B4%20%D1%81%D0%BA%D1%80%D1%8B%D1%82%D1%8B%D0%B9%20%D0%BA%D0%B0%D1%80%D0%BD%D0%B8%D0%B7 | N45: не проверено | O45: 2026-09-11 | P45: уточнить | Q45: Через Авито можно посмотреть предложения по Саратову и оптимизировать стоимость: откройте поиск по ссылке, сравните с ценой в смете и с вариантами магазинов выше. Автоматически цены с Авито снять нельзя (доступ по IP ограничен) — смотреть вручную.
A46: 1_Ремонт | B46: 11 | C46: 3. Сантехника | D46: Унитаз | E46: шт | F46: МИН | G46: Cersanit Trento 011 3/6 TPL, сиденье с микролифтом | H46: 7990 | I46: 8000 | J46: -0.1 | K46: Сантехника.ру Саратов | L46: Саратов | M46: https://saratov.santehnica.ru/product/1491701.html | N46: страница | O46: 2026-09-11 | P46: ок | Q46: Лемана ПРО (Москва-сайт) — 7 353 ₽ за S-KO-TR011-3/6-PL-w; саратовская карточка Лемана не открылась (401)
A47: 1_Ремонт | B47: 11 | C47: 3. Сантехника | D47: Унитаз | E47: шт | F47: СРЕД | G47: Cersanit City Clean On 011 3/5 DPL EO slim, безободковый, микролифт | H47: 12520 | I47: 18000 | J47: -30.4 | K47: Сантехника.ру Саратов | L47: Саратов | M47: https://saratov.santehnica.ru/product/357399.html | N47: страница | O47: 2026-09-11 | P47: ок | Q47: Та же цена на cersanit.ru; Roca Gap Clean Rim не проверялся
A48: 1_Ремонт | B48: 11 | C48: 3. Сантехника | D48: Унитаз | E48: шт | F48: МАКС | G48: Инсталляция Geberit Duofix + подвесной Geberit Smyle Square + клавиша (комплект) | H48: 83574 | I48: 45000 | J48: 85.7 | K48: Сантехника.ру Саратов | L48: Саратов | M48: https://saratov.santehnica.ru/product/1034211.html | N48: страница | O48: 2026-09-11 | P48: ок | Q48: Комплект с iCon на странице не выделен; готовые комплекты Geberit 83–87 тыс — смета МАКС 45 000 занижена; альтернатива — Duofix + унитаз Cersanit/Roca (категория «унитаз с инсталляцией Geberit от 16 793 ₽», сниппет)
A49: 1_Ремонт | B49: 11 | C49: 3. Сантехника | D49: Унитаз | E49: шт | F49: ВСЕ | G49: Авито Саратов — поиск «Унитаз» (новые товары магазинов и объявления) | K49: Авито Саратов | L49: Саратов | M49: https://www.avito.ru/saratov?q=%D0%A3%D0%BD%D0%B8%D1%82%D0%B0%D0%B7 | N49: не проверено | O49: 2026-09-11 | P49: уточнить | Q49: Через Авито можно посмотреть предложения по Саратову и оптимизировать стоимость: откройте поиск по ссылке, сравните с ценой в смете и с вариантами магазинов выше. Автоматически цены с Авито снять нельзя (доступ по IP ограничен) — смотреть вручную.
A50: 1_Ремонт | B50: 12 | C50: 3. Сантехника | D50: Раковина (умывальник) | E50: шт | F50: МИН | G50: Santek Анимо 60 (60×48), 1.WH11.0.508 | H50: 2990 | I50: 3000 | J50: -0.3 | K50: Сантехника.ру Саратов | L50: Саратов | M50: https://saratov.santehnica.ru/product/80957.html | N50: страница | O50: 2026-09-11 | P50: ок | Q50: Santek Анимо 55 — 2 890 ₽
A51: 1_Ремонт | B51: 12 | C51: 3. Сантехника | D51: Раковина (умывальник) | E51: шт | F51: СРЕД | G51: Roca Debba 55 с пьедесталом | H51: 7860 | I51: 8000 | J51: -1.8 | K51: Сантехника.ру Саратов | L51: Саратов | M51: https://saratov.santehnica.ru/product/200516.html | N51: страница | O51: 2026-09-11 | P51: ок | Q51: Cersanit Como 70 — 6 290 ₽; Roca Gap 60 отдельно не подтверждён
A52: 1_Ремонт | B52: 12 | C52: 3. Сантехника | D52: Раковина (умывальник) | E52: шт | F52: МАКС | G52: Jacob Delafon Vivienne 60 | H52: 24852 | I52: 18000 | J52: 38.1 | K52: Сантехника.ру Саратов | L52: Саратов | M52: https://saratov.santehnica.ru/product/316111.html | N52: страница | O52: 2026-09-11 | P52: ок | Q52: Villeroy&Boch O.novo 60 — 24 975 ₽
A53: 1_Ремонт | B53: 12 | C53: 3. Сантехника | D53: Раковина (умывальник) | E53: шт | F53: ВСЕ | G53: Авито Саратов — поиск «Раковина» (новые товары магазинов и объявления) | K53: Авито Саратов | L53: Саратов | M53: https://www.avito.ru/saratov?q=%D0%A0%D0%B0%D0%BA%D0%BE%D0%B2%D0%B8%D0%BD%D0%B0 | N53: не проверено | O53: 2026-09-11 | P53: уточнить | Q53: Через Авито можно посмотреть предложения по Саратову и оптимизировать стоимость: откройте поиск по ссылке, сравните с ценой в смете и с вариантами магазинов выше. Автоматически цены с Авито снять нельзя (доступ по IP ограничен) — смотреть вручную.
A54: 1_Ремонт | B54: 13 | C54: 3. Сантехника | D54: Смеситель для раковины | E54: шт | F54: МИН | G54: Lemark Plus Advance LM1206C (монолитный) | H54: 2410 | I54: 2500 | J54: -3.6 | K54: Сантехника-Онлайн | L54: доставка в Саратов | M54: https://santehnika-online.ru/product/smesitel_lemark_plus_advance_lm1206c_dlya_rakoviny/ | N54: сниппет | O54: 2026-09-11 | P54: ок | Q54: Iddis Odda ODDWT00i01 — 4 700 ₽ (Лемана ПРО, Москва-сайт); «Iddis Sena 690 ₽» на Сантехника.ру Саратов выглядит как ошибка/неполный товар — не брать
A55: 1_Ремонт | B55: 13 | C55: 3. Сантехника | D55: Смеситель для раковины | E55: шт | F55: СРЕД | G55: Lemark Plus Advance LM1116C | H55: 8619 | I55: 7000 | J55: 23.1 | K55: Сантехника.ру Саратов | L55: Саратов | M55: https://saratov.santehnica.ru/product/105713.html | N55: страница | O55: 2026-09-11 | P55: ок | Q55: Hansgrohe Logis 71101000 — 11 920 ₽ там же; Lemark Plus Grace LM1506C — 4 672 ₽; Grohe BauEdge не проверен
A56: 1_Ремонт | B56: 13 | C56: 3. Сантехника | D56: Смеситель для раковины | E56: шт | F56: МАКС | G56: Hansgrohe Talis E 71710000 | H56: 17768 | I56: 18000 | J56: -1.3 | K56: ENTERO.RU | L56: доставка в Саратов | M56: https://entero.ru/item/159848 | N56: сниппет | O56: 2026-09-11 | P56: ок | Q56: В Саратове (Сантехника.ру, страница): Hansgrohe Vernis Blend 71551000 — 12 629 ₽, Logis Fine 71253000 — 14 676 ₽; разброс по Talis E 17 768–26 047 ₽
A57: 1_Ремонт | B57: 13 | C57: 3. Сантехника | D57: Смеситель для раковины | E57: шт | F57: ВСЕ | G57: Авито Саратов — поиск «Смеситель для раковины» (новые товары магазинов и объявления) | K57: Авито Саратов | L57: Саратов | M57: https://www.avito.ru/saratov?q=%D0%A1%D0%BC%D0%B5%D1%81%D0%B8%D1%82%D0%B5%D0%BB%D1%8C%20%D0%B4%D0%BB%D1%8F%20%D1%80%D0%B0%D0%BA%D0%BE%D0%B2%D0%B8%D0%BD%D1%8B | N57: не проверено | O57: 2026-09-11 | P57: уточнить | Q57: Через Авито можно посмотреть предложения по Саратову и оптимизировать стоимость: откройте поиск по ссылке, сравните с ценой в смете и с вариантами магазинов выше. Автоматически цены с Авито снять нельзя (доступ по IP ограничен) — смотреть вручную.
A58: 1_Ремонт | B58: 14 | C58: 3. Сантехника | D58: Сифон + подводки для раковины | E58: шт | F58: МИН | G58: Бутылочный сифон пластик (АНИ Пласт/Unicorn) + 2 гибкие подводки | I58: 700 | K58: Лемана ПРО Саратов | L58: Саратов | M58: https://saratov.lemanapro.ru/catalogue/sifony/butylochnye-dlya-rakoviny/ | N58: сниппет | O58: 2026-09-11 | P58: уточнить | Q58: Категория «бутылочные сифоны от 134 ₽» (сниппет), конкретная модель и подводка не подтверждены; сайт Лемана блокирует загрузку (401)
A59: 1_Ремонт | B59: 14 | C59: 3. Сантехника | D59: Сифон + подводки для раковины | E59: шт | F59: СРЕД | G59: Сифон Unicorn ABS с регулировкой высоты + подводки | I59: 1500 | K59: Ozon | L59: доставка в Саратов | M59: https://www.ozon.ru/category/sifony-dlya-santehniki-10312/unicorn-87304659/ | N59: сниппет | O59: 2026-09-11 | P59: уточнить | Q59: Сниппет Ozon: Unicorn 506–1 241 ₽ без привязки к модели; цена комплекта не подтверждена
A60: 1_Ремонт | B60: 14 | C60: 3. Сантехника | D60: Сифон + подводки для раковины | E60: шт | F60: МАКС | G60: Сифон McAlpine / Geberit хром + подводки в оплётке | I60: 3500 | K60: Яндекс Маркет | L60: доставка в Саратов | M60: https://market.yandex.ru/category/sifony-dlya-rakovin | N60: не проверено | O60: 2026-09-11 | P60: уточнить | Q60: Цены в сниппетах не показаны
A61: 1_Ремонт | B61: 14 | C61: 3. Сантехника | D61: Сифон + подводки для раковины | E61: шт | F61: ВСЕ | G61: Авито Саратов — поиск «Сифон + подводки для раковины» (новые товары магазинов и объявления) | K61: Авито Саратов | L61: Саратов | M61: https://www.avito.ru/saratov?q=%D0%A1%D0%B8%D1%84%D0%BE%D0%BD%20%2B%20%D0%BF%D0%BE%D0%B4%D0%B2%D0%BE%D0%B4%D0%BA%D0%B8%20%D0%B4%D0%BB%D1%8F%20%D1%80%D0%B0%D0%BA%D0%BE%D0%B2%D0%B8%D0%BD%D1%8B | N61: не проверено | O61: 2026-09-11 | P61: уточнить | Q61: Через Авито можно посмотреть предложения по Саратову и оптимизировать стоимость: откройте поиск по ссылке, сравните с ценой в смете и с вариантами магазинов выше. Автоматически цены с Авито снять нельзя (доступ по IP ограничен) — смотреть вручную.
A62: 1_Ремонт | B62: 15 | C62: 3. Сантехника | D62: Тумба под раковину | E62: шт | F62: МИН | G62: Тумба Руан напольная 57 см + раковина Cersanit Colour 60 (комплект) | H62: 11500 | I62: 6000 | J62: 91.7 | K62: Лемана ПРО Саратов | L62: Саратов | M62: https://saratov.lemanapro.ru/set/tumba-pod-rakovinu-ruan-napolnaya-57-sm-cvet-belyy-dub-sonoma-s-rakovinoy-cersanit-colour-keramika-60-sm-cvet-belyy-89432379/ | N62: сниппет | O62: 2026-09-11 | P62: ок | Q62: Цена именно для Саратова, но включает раковину (в смете раковина отдельной строкой); Sensea отдельно не подтверждён (401)
A63: 1_Ремонт | B63: 15 | C63: 3. Сантехника | D63: Тумба под раковину | E63: шт | F63: СРЕД | G63: Aquaton Онда 60 подвесная 1A122801ON010 (без раковины) | H63: 12490 | I63: 18000 | J63: -30.6 | K63: Сантехника.ру Саратов | L63: Саратов | M63: https://saratov.santehnica.ru/product/54261.html | N63: страница | O63: 2026-09-11 | P63: ок | Q63: Aquaton Нортон 80 подвесная — 18 990 ₽; Aquaton Hope 60 — 18 650 ₽ (Сантехника-Онлайн, сниппет)
A64: 1_Ремонт | B64: 15 | C64: 3. Сантехника | D64: Тумба под раковину | E64: шт | F64: МАКС | G64: Jacob Delafon Tolbiac 60 EB2381-J5 (без раковины) | H64: 23921 | I64: 45000 | J64: -46.8 | K64: Сантехника.ру Саратов | L64: Саратов | M64: https://saratov.santehnica.ru/product/350955.html | N64: страница | O64: 2026-09-11 | P64: ок | Q64: Tolbiac 80 EB2382-J5 — 26 087 ₽; Cezares не проверен
A65: 1_Ремонт | B65: 15 | C65: 3. Сантехника | D65: Тумба под раковину | E65: шт | F65: ВСЕ | G65: Авито Саратов — поиск «Тумба под раковину» (новые товары магазинов и объявления) | K65: Авито Саратов | L65: Саратов | M65: https://www.avito.ru/saratov?q=%D0%A2%D1%83%D0%BC%D0%B1%D0%B0%20%D0%BF%D0%BE%D0%B4%20%D1%80%D0%B0%D0%BA%D0%BE%D0%B2%D0%B8%D0%BD%D1%83 | N65: не проверено | O65: 2026-09-11 | P65: уточнить | Q65: Через Авито можно посмотреть предложения по Саратову и оптимизировать стоимость: откройте поиск по ссылке, сравните с ценой в смете и с вариантами магазинов выше. Автоматически цены с Авито снять нельзя (доступ по IP ограничен) — смотреть вручную.
A66: 1_Ремонт | B66: 16 | C66: 3. Сантехника | D66: Смеситель для душа + душевая стойка | E66: компл | F66: МИН | G66: Iddis Axes 003WTS0i08 душевая стойка со смесителем | H66: 7190 | I66: 4000 | J66: 79.8 | K66: Сантехника.ру Саратов | L66: Саратов | M66: https://saratov.santehnica.ru/product/350555.html | N66: страница | O66: 2026-09-11 | P66: ок | Q66: Цена со скидкой 40%; ESKO St300 в Лемана ПРО Саратов есть, цена не получена (401)
A67: 1_Ремонт | B67: 16 | C67: 3. Сантехника | D67: Смеситель для душа + душевая стойка | E67: компл | F67: СРЕД | G67: Lemark Tropic LM7002C душевая система | H67: 15830 | I67: 15000 | J67: 5.5 | K67: Wodolei.ru | L67: доставка в Саратов | M67: https://wodolei.ru/catalog/dushevie_paneli/lemark-tropic-lm7002c-161890-item/ | N67: сниппет | O67: 2026-09-11 | P67: ок | Q67: В Саратове (Сантехника.ру, страница): Lemark Tropic LM7010C с термостатом — 28 826 ₽, Linara LM0462C — 25 490 ₽; разброс по LM7002C 15 830–26 459 ₽
A68: 1_Ремонт | B68: 16 | C68: 3. Сантехника | D68: Смеситель для душа + душевая стойка | E68: компл | F68: МАКС | G68: Hansgrohe Crometta S 240 Showerpipe 27267000 | H68: 61911 | I68: 45000 | J68: 37.6 | K68: Сантехника.ру Саратов | L68: Саратов | M68: https://saratov.santehnica.ru/product/100552.html | N68: страница | O68: 2026-09-11 | P68: ок | Q68: Croma Select S 280 — 121–129 тыс ₽ (сниппет), вне бюджета
A69: 1_Ремонт | B69: 16 | C69: 3. Сантехника | D69: Смеситель для душа + душевая стойка | E69: компл | F69: ВСЕ | G69: Авито Саратов — поиск «Смеситель для душа + душевая стойка» (новые товары магазинов и объявления) | K69: Авито Саратов | L69: Саратов | M69: https://www.avito.ru/saratov?q=%D0%A1%D0%BC%D0%B5%D1%81%D0%B8%D1%82%D0%B5%D0%BB%D1%8C%20%D0%B4%D0%BB%D1%8F%20%D0%B4%D1%83%D1%88%D0%B0%20%2B%20%D0%B4%D1%83%D1%88%D0%B5%D0%B2%D0%B0%D1%8F%20%D1%81%D1%82%D0%BE%D0%B9%D0%BA%D0%B0 | N69: не проверено | O69: 2026-09-11 | P69: уточнить | Q69: Через Авито можно посмотреть предложения по Саратову и оптимизировать стоимость: откройте поиск по ссылке, сравните с ценой в смете и с вариантами магазинов выше. Автоматически цены с Авито снять нельзя (доступ по IP ограничен) — смотреть вручную.
A70: 1_Ремонт | B70: 17 | C70: 3. Сантехника | D70: Ограждение душевого подиума | E70: шт | F70: МИН | G70: Штанга для шторки + шторка | I70: 3000 | K70: Лемана ПРО Саратов | L70: Саратов | M70: https://saratov.lemanapro.ru/catalogue/shtorki-dlya-vannoy/ | N70: сниппет | O70: 2026-09-11 | P70: уточнить | Q70: Категории: штанги прямые от 125 ₽, угловые от 1 041 ₽, шторки 75 см от 1 260 ₽ (сниппеты, не Саратов); комплект не подтверждён
A71: 1_Ремонт | B71: 17 | C71: 3. Сантехника | D71: Ограждение душевого подиума | E71: шт | F71: СРЕД | G71: Стекло 8 мм закалённое Walk-In на заказ | I71: 30000 | K71: АРТ-ЛАЙН (Саратов) | L71: Саратов | M71: https://art-line.ru/dushevyie-peregorodki.html | N71: страница | O71: 2026-09-11 | P71: уточнить | Q71: На сайте цен нет — расчёт по звонку 8 (905) 38-39-555; монтаж отдельно по Профи.ру Саратов 1 540–8 620 ₽ (сниппет)
A72: 1_Ремонт | B72: 17 | C72: 3. Сантехника | D72: Ограждение душевого подиума | E72: шт | F72: МАКС | G72: Стекло 10 мм + распашная дверь, чёрная/латунная фурнитура | I72: 60000 | K72: АРТ-ЛАЙН (Саратов) | L72: Саратов | M72: https://art-line.ru/dushevyie-peregorodki.html | N72: страница | O72: 2026-09-11 | P72: уточнить | Q72: Цен нет, по запросу; готовые перегородки santehnica.ru 13 931–25 500 ₽ (сниппет, без установки)
A73: 1_Ремонт | B73: 17 | C73: 3. Сантехника | D73: Ограждение душевого подиума | E73: шт | F73: ВСЕ | G73: Авито Саратов — поиск «Ограждение душевого подиума» (новые товары магазинов и объявления) | K73: Авито Саратов | L73: Саратов | M73: https://www.avito.ru/saratov?q=%D0%9E%D0%B3%D1%80%D0%B0%D0%B6%D0%B4%D0%B5%D0%BD%D0%B8%D0%B5%20%D0%B4%D1%83%D1%88%D0%B5%D0%B2%D0%BE%D0%B3%D0%BE%20%D0%BF%D0%BE%D0%B4%D0%B8%D1%83%D0%BC%D0%B0 | N73: не проверено | O73: 2026-09-11 | P73: уточнить | Q73: Через Авито можно посмотреть предложения по Саратову и оптимизировать стоимость: откройте поиск по ссылке, сравните с ценой в смете и с вариантами магазинов выше. Автоматически цены с Авито снять нельзя (доступ по IP ограничен) — смотреть вручную.
A74: 1_Ремонт | B74: 18 | C74: 3. Сантехника | D74: Гигиенический душ | E74: компл | F74: МИН | G74: Shevanik S9905T-1 со смесителем | H74: 6492 | I74: 2500 | J74: 159.7 | K74: Лемана ПРО (Москва-сайт) | L74: доставка в Саратов | M74: https://lemanapro.ru/product/gigienicheskiy-dush-so-smesitelem-shevanik-s9905t-1-91477406/ | N74: сниппет | O74: 2026-09-11 | P74: ок | Q74: Категория Лемана «смесители с гиг. душем от 2 346 ₽» — модель за ~2 500 не подтверждена; Саратов 401
A75: 1_Ремонт | B75: 18 | C75: 3. Сантехника | D75: Гигиенический душ | E75: компл | F75: СРЕД | G75: Lemark Pramen LM3318C со смесителем | H75: 7436 | I75: 7000 | J75: 6.2 | K75: Сантехника.ру Саратов | L75: Саратов | M75: https://saratov.santehnica.ru/product/88648.html | N75: страница | O75: 2026-09-11 | P75: ок | Q75: Iddis 003SBR0i08 — 8 990 ₽; Lemark Solo LM7165C — 9 874 ₽
A76: 1_Ремонт | B76: 18 | C76: 3. Сантехника | D76: Гигиенический душ | E76: компл | F76: МАКС | G76: Hansgrohe Bidette S 1jet 29232000 | H76: 15852 | I76: 15000 | J76: 5.7 | K76: Сантехника.ру Саратов | L76: Саратов | M76: https://saratov.santehnica.ru/product/462683.html | N76: страница | O76: 2026-09-11 | P76: ок
A77: 1_Ремонт | B77: 18 | C77: 3. Сантехника | D77: Гигиенический душ | E77: компл | F77: ВСЕ | G77: Авито Саратов — поиск «Гигиенический душ» (новые товары магазинов и объявления) | K77: Авито Саратов | L77: Саратов | M77: https://www.avito.ru/saratov?q=%D0%93%D0%B8%D0%B3%D0%B8%D0%B5%D0%BD%D0%B8%D1%87%D0%B5%D1%81%D0%BA%D0%B8%D0%B9%20%D0%B4%D1%83%D1%88 | N77: не проверено | O77: 2026-09-11 | P77: уточнить | Q77: Через Авито можно посмотреть предложения по Саратову и оптимизировать стоимость: откройте поиск по ссылке, сравните с ценой в смете и с вариантами магазинов выше. Автоматически цены с Авито снять нельзя (доступ по IP ограничен) — смотреть вручную.
A78: 1_Ремонт | B78: 19 | C78: 3. Сантехника | D78: Полотенцесушитель электрический | E78: шт | F78: МИН | G78: Terminus M-образный 400×500 электрический | H78: 3440 | I78: 4000 | J78: -14 | K78: Сантехника.ру Саратов | L78: Саратов | M78: https://saratov.santehnica.ru/product/101158.html | N78: страница | O78: 2026-09-11 | P78: ок | Q78: Domoterm DMT 103-25 — 6 900 ₽
A79: 1_Ремонт | B79: 19 | C79: 3. Сантехника | D79: Полотенцесушитель электрический | E79: шт | F79: СРЕД | G79: Indigo Arc с полкой Electro 40×60 | H79: 11438 | I79: 12000 | J79: -4.7 | K79: Сантехника.ру Саратов | L79: Саратов | M79: https://saratov.santehnica.ru/product/262819.html | N79: страница | O79: 2026-09-11 | P79: ок | Q79: Indigo Arc Electro 40×60 без полки — 9 158 ₽; Terminus Аврора П8 400×850 — 13 820 ₽
A80: 1_Ремонт | B80: 19 | C80: 3. Сантехника | D80: Полотенцесушитель электрический | E80: шт | F80: МАКС | G80: Ника Step-1 50×80 | H80: 19070 | I80: 25000 | J80: -23.7 | K80: Сантехника.ру Саратов | L80: Саратов | M80: https://saratov.santehnica.ru/product/815401.html | N80: страница | O80: 2026-09-11 | P80: ок | Q80: Сунержа Нюанс 3.0 1800 — 32 200 ₽; Маргроид Инаро 12×120 — 17 208 ₽
A81: 1_Ремонт | B81: 19 | C81: 3. Сантехника | D81: Полотенцесушитель электрический | E81: шт | F81: ВСЕ | G81: Авито Саратов — поиск «Полотенцесушитель электрический» (новые товары магазинов и объявления) | K81: Авито Саратов | L81: Саратов | M81: https://www.avito.ru/saratov?q=%D0%9F%D0%BE%D0%BB%D0%BE%D1%82%D0%B5%D0%BD%D1%86%D0%B5%D1%81%D1%83%D1%88%D0%B8%D1%82%D0%B5%D0%BB%D1%8C%20%D1%8D%D0%BB%D0%B5%D0%BA%D1%82%D1%80%D0%B8%D1%87%D0%B5%D1%81%D0%BA%D0%B8%D0%B9 | N81: не проверено | O81: 2026-09-11 | P81: уточнить | Q81: Через Авито можно посмотреть предложения по Саратову и оптимизировать стоимость: откройте поиск по ссылке, сравните с ценой в смете и с вариантами магазинов выше. Автоматически цены с Авито снять нельзя (доступ по IP ограничен) — смотреть вручную.
A82: 1_Ремонт | B82: 20 | C82: 3. Сантехника | D82: Зеркало / зеркальный шкаф | E82: шт | F82: МИН | G82: Aquanet Донна зеркальный шкаф 60 (без подсветки) | H82: 6699 | I82: 1500 | J82: 346.6 | K82: Сантехника.ру Саратов | L82: Саратов | M82: https://saratov.santehnica.ru/product/143402.html | N82: страница | O82: 2026-09-11 | P82: ок | Q82: Отклонение из-за класса товара: смета МИН = простое зеркало; зеркало 60 см без шкафа не проверено (Лемана категория «от 2 100 ₽», сниппет)
A83: 1_Ремонт | B83: 20 | C83: 3. Сантехника | D83: Зеркало / зеркальный шкаф | E83: шт | F83: СРЕД | G83: Stella Polar Концепт Лаура 60/C с подсветкой | H83: 7528 | I83: 6000 | J83: 25.5 | K83: Сантехника.ру Саратов | L83: Саратов | M83: https://saratov.santehnica.ru/product/233414.html | N83: страница | O83: 2026-09-11 | P83: ок | Q83: Style Line Амарант — 8 210 ₽
A84: 1_Ремонт | B84: 20 | C84: 3. Сантехника | D84: Зеркало / зеркальный шкаф | E84: шт | F84: МАКС | G84: Style Line El Fante Каре 60 | H84: 12024 | I84: 15000 | J84: -19.8 | K84: Сантехника.ру Саратов | L84: Саратов | M84: https://saratov.santehnica.ru/product/248752.html | N84: страница | O84: 2026-09-11 | P84: ок | Q84: BelBagno Marino — 18 800 ₽; Vigo Geometry Comfort 60 — 13 500 ₽ (сниппет)
A85: 1_Ремонт | B85: 20 | C85: 3. Сантехника | D85: Зеркало / зеркальный шкаф | E85: шт | F85: ВСЕ | G85: Авито Саратов — поиск «Зеркало / зеркальный шкаф» (новые товары магазинов и объявления) | K85: Авито Саратов | L85: Саратов | M85: https://www.avito.ru/saratov?q=%D0%97%D0%B5%D1%80%D0%BA%D0%B0%D0%BB%D0%BE%20/%20%D0%B7%D0%B5%D1%80%D0%BA%D0%B0%D0%BB%D1%8C%D0%BD%D1%8B%D0%B9%20%D1%88%D0%BA%D0%B0%D1%84 | N85: не проверено | O85: 2026-09-11 | P85: уточнить | Q85: Через Авито можно посмотреть предложения по Саратову и оптимизировать стоимость: откройте поиск по ссылке, сравните с ценой в смете и с вариантами магазинов выше. Автоматически цены с Авито снять нельзя (доступ по IP ограничен) — смотреть вручную.
A86: 1_Ремонт | B86: 21 | C86: 3. Сантехника | D86: Вентилятор вытяжной | E86: шт | F86: МИН | G86: Осевой 100 мм (Эра/Вентс) | I86: 800 | K86: Лемана ПРО Саратов | L86: Саратов | M86: https://saratov.lemanapro.ru/catalogue/ventilyatory-vytyazhnye/100/ | N86: сниппет | O86: 2026-09-11 | P86: уточнить | Q86: Категория «100 мм от 655 ₽» (сниппет, Хабаровск); модель не подтверждена
A87: 1_Ремонт | B87: 21 | C87: 3. Сантехника | D87: Вентилятор вытяжной | E87: шт | F87: СРЕД | G87: Electrolux Rainbow EAFR-100 (обратный клапан) | H87: 2830 | I87: 3000 | J87: -5.7 | K87: E-Katalog (агрегатор) | L87: доставка в Саратов | M87: https://www.e-katalog.ru/ELECTROLUX-RAINBOW-EAFR-100.htm | N87: сниппет | O87: 2026-09-11 | P87: ок | Q87: Диапазон 2 830–3 699 ₽; есть в Лемана ПРО, цена не получена
A88: 1_Ремонт | B88: 21 | C88: 3. Сантехника | D88: Вентилятор вытяжной | E88: шт | F88: МАКС | G88: Soler&Palau Silent-100 CRZ с таймером | H88: 4316 | I88: 7000 | J88: -38.3 | K88: Vivaset | L88: доставка в Саратов | M88: https://vivaset.ru/products/solerpalau-silent-100-crz.html | N88: сниппет | O88: 2026-09-11 | P88: ок | Q88: Диапазон по магазинам 4 316–6 480 ₽
A89: 1_Ремонт | B89: 21 | C89: 3. Сантехника | D89: Вентилятор вытяжной | E89: шт | F89: ВСЕ | G89: Авито Саратов — поиск «Вентилятор вытяжной» (новые товары магазинов и объявления) | K89: Авито Саратов | L89: Саратов | M89: https://www.avito.ru/saratov?q=%D0%92%D0%B5%D0%BD%D1%82%D0%B8%D0%BB%D1%8F%D1%82%D0%BE%D1%80%20%D0%B2%D1%8B%D1%82%D1%8F%D0%B6%D0%BD%D0%BE%D0%B9 | N89: не проверено | O89: 2026-09-11 | P89: уточнить | Q89: Через Авито можно посмотреть предложения по Саратову и оптимизировать стоимость: откройте поиск по ссылке, сравните с ценой в смете и с вариантами магазинов выше. Автоматически цены с Авито снять нельзя (доступ по IP ограничен) — смотреть вручную.
A90: 1_Ремонт | B90: 22 | C90: 3. Сантехника | D90: Аксессуары (держатели, ёршик, крючки, дозатор) | E90: компл | F90: МИН | G90: Набор Iddis (крючки/держатели/ёршик) | I90: 2500 | K90: Сантехника.ру Саратов | L90: Саратов | M90: https://saratov.santehnica.ru/brand/iddis/ | N90: страница | O90: 2026-09-11 | P90: уточнить | Q90: Подтверждён только набор 4 крючка Iddis HOK4SC0i41 — 1 690 ₽; полный комплект не собран
A91: 1_Ремонт | B91: 22 | C91: 3. Сантехника | D91: Аксессуары (держатели, ёршик, крючки, дозатор) | E91: компл | F91: СРЕД | G91: Grohe Essentials 40407001 набор аксессуаров | H91: 11530 | I91: 7000 | J91: 64.7 | K91: SantehMoll | L91: доставка в Саратов | M91: https://santehmoll.ru/product/basic_nabor_aksessuarov/ | N91: сниппет | O91: 2026-09-11 | P91: ок
A92: 1_Ремонт | B92: 22 | C92: 3. Сантехника | D92: Аксессуары (держатели, ёршик, крючки, дозатор) | E92: компл | F92: МАКС | G92: Grohe Essentials 40344DC1 суперсталь (5 предметов) | H92: 21672 | I92: 20000 | J92: 8.4 | K92: ТОП-Сантехника | L92: доставка в Саратов | M92: https://top-santehnika.ru/product/nabor-aksessuarov-dlya-vanny-grohe-essentials-40344dc1/ | N92: сниппет | O92: 2026-09-11 | P92: ок
A93: 1_Ремонт | B93: 22 | C93: 3. Сантехника | D93: Аксессуары (держатели, ёршик, крючки, дозатор) | E93: компл | F93: ВСЕ | G93: Авито Саратов — поиск «Аксессуары» (новые товары магазинов и объявления) | K93: Авито Саратов | L93: Саратов | M93: https://www.avito.ru/saratov?q=%D0%90%D0%BA%D1%81%D0%B5%D1%81%D1%81%D1%83%D0%B0%D1%80%D1%8B | N93: не проверено | O93: 2026-09-11 | P93: уточнить | Q93: Через Авито можно посмотреть предложения по Саратову и оптимизировать стоимость: откройте поиск по ссылке, сравните с ценой в смете и с вариантами магазинов выше. Автоматически цены с Авито снять нельзя (доступ по IP ограничен) — смотреть вручную.
A94: 1_Ремонт | B94: 23 | C94: 3. Сантехника | D94: Люк ревизионный к колонке/стоякам | E94: шт | F94: МИН | G94: Пластиковый люк открытого типа 30×30 | I94: 2000 | K94: Лемана ПРО Саратов | L94: Саратов | M94: https://saratov.lemanapro.ru/catalogue/revizionnye-lyuki-otkrytogo-tipa/plastikovye/ | N94: сниппет | O94: 2026-09-11 | P94: уточнить | Q94: Категория «люки для ванной от 359 ₽» (сниппет); модель не подтверждена
A95: 1_Ремонт | B95: 23 | C95: 3. Сантехника | D95: Люк ревизионный к колонке/стоякам | E95: шт | F95: СРЕД | G95: Хаммер под плитку 40×60 (распашной) | I95: 5000 | K95: ВсеИнструменты | L95: доставка в Саратов | M95: https://www.vseinstrumenti.ru/category/revizionnye-lyuki-171513/hammer-2068594/ | N95: сниппет | O95: 2026-09-11 | P95: уточнить | Q95: Категория «Хаммер от 2 350 ₽» (сниппет); конкретный размер не подтверждён
A96: 1_Ремонт | B96: 23 | C96: 3. Сантехника | D96: Люк ревизионный к колонке/стоякам | E96: шт | F96: МАКС | G96: Хаммер Слава нажимной скрытый алюминий 60×60 | H96: 13999 | I96: 12000 | J96: 16.7 | K96: Лемана ПРО | L96: доставка в Саратов | M96: https://klin.lemanapro.ru/product/lyuk-revizionnyy-skrytyy-nazhimnoy-hammer-slava-alyuminiy-60x60sm-90162136/ | N96: сниппет | O96: 2026-09-11 | P96: ок | Q96: Цена по сниппету региона Клин; Лючки.РФ Секрет 3.0 50×70 — 18 235 ₽ (Новокузнецк)
A97: 1_Ремонт | B97: 23 | C97: 3. Сантехника | D97: Люк ревизионный к колонке/стоякам | E97: шт | F97: ВСЕ | G97: Авито Саратов — поиск «Люк ревизионный к колонке/стоякам» (новые товары магазинов и объявления) | K97: Авито Саратов | L97: Саратов | M97: https://www.avito.ru/saratov?q=%D0%9B%D1%8E%D0%BA%20%D1%80%D0%B5%D0%B2%D0%B8%D0%B7%D0%B8%D0%BE%D0%BD%D0%BD%D1%8B%D0%B9%20%D0%BA%20%D0%BA%D0%BE%D0%BB%D0%BE%D0%BD%D0%BA%D0%B5/%D1%81%D1%82%D0%BE%D1%8F%D0%BA%D0%B0%D0%BC | N97: не проверено | O97: 2026-09-11 | P97: уточнить | Q97: Через Авито можно посмотреть предложения по Саратову и оптимизировать стоимость: откройте поиск по ссылке, сравните с ценой в смете и с вариантами магазинов выше. Автоматически цены с Авито снять нельзя (доступ по IP ограничен) — смотреть вручную.
A98: 1_Ремонт | B98: 24 | C98: 3. Сантехника | D98: Расходники (краны, гибкая подводка, ФУМ, силикон) | E98: компл | F98: МИН | G98: Краны шаровые 1/2 ×4 + подводка + ФУМ + герметик | I98: 3000 | K98: Лемана ПРО Саратов | L98: Саратов | M98: https://saratov.lemanapro.ru/catalogue/sharovye-krany/1-2-dyuyma/ | N98: сниппет | O98: 2026-09-11 | P98: уточнить | Q98: Краны 1/2 «от 136 ₽» (сниппет); подводка и герметик без цен; сайт 401
A99: 1_Ремонт | B99: 24 | C99: 3. Сантехника | D99: Расходники (краны, гибкая подводка, ФУМ, силикон) | E99: компл | F99: СРЕД | G99: То же, краны Stout/Valtec, подводка в нерж. оплётке | I99: 6000 | K99: Лемана ПРО Саратов | L99: Саратов | M99: https://saratov.lemanapro.ru/catalogue/podvodka-dlya-vody/ | N99: не проверено | O99: 2026-09-11 | P99: уточнить | Q99: Цены не показаны
A100: 1_Ремонт | B100: 24 | C100: 3. Сантехника | D100: Расходники (краны, гибкая подводка, ФУМ, силикон) | E100: компл | F100: МАКС | G100: То же, краны Bugatti, сильфонная подводка | I100: 10000 | K100: Лемана ПРО Саратов | L100: Саратов | M100: https://saratov.lemanapro.ru/catalogue/sharovye-krany/1-2-dyuyma/ | N100: не проверено | O100: 2026-09-11 | P100: уточнить | Q100: Цены не показаны
A101: 1_Ремонт | B101: 24 | C101: 3. Сантехника | D101: Расходники (краны, гибкая подводка, ФУМ, силикон) | E101: компл | F101: ВСЕ | G101: Авито Саратов — поиск «Расходники» (новые товары магазинов и объявления) | K101: Авито Саратов | L101: Саратов | M101: https://www.avito.ru/saratov?q=%D0%A0%D0%B0%D1%81%D1%85%D0%BE%D0%B4%D0%BD%D0%B8%D0%BA%D0%B8 | N101: не проверено | O101: 2026-09-11 | P101: уточнить | Q101: Через Авито можно посмотреть предложения по Саратову и оптимизировать стоимость: откройте поиск по ссылке, сравните с ценой в смете и с вариантами магазинов выше. Автоматически цены с Авито снять нельзя (доступ по IP ограничен) — смотреть вручную.
...
